{
  "info": {
    "key": "g588_0118"
  },
  "sheets": {
    "מזומנים": {
      "columns": [
        "שם המנפיק/שם נייר ערך",
        "מספר ני\"ע",
        "מספר מנפיק",
        "דירוג",
        "שם מדרג",
        "סוג מטבע",
        "שיעור ריבית",
        "תשואה לפידיון",
        "שווי שוק",
        "שעור מנכסי אפיק ההשקעה",
        "שעור מסך נכסי השקעה"
      ],
      "data": [
        [
          "עו'ש- לאומי",
          "1111111111- 10- לאומי",
          10,
          "AAA.IL",
          "S&P מעלות",
          "שקל חדש",
          0,
          0,
          7795.60541,
          89.89,
          3.44
        ],
        [
          "דולר- לאומי",
          "20001- 10- לאומי",
          10,
          "AAA.IL",
          "S&P מעלות",
          "דולר אמריקאי",
          0,
          0,
          875.33114508,
          10.09,
          0.39
        ],
        [
          "יורו- לאומי",
          "20003- 10- לאומי",
          10,
          "AAA.IL",
          "S&P מעלות",
          "אירו",
          0,
          0,
          0.544000296,
          0.01,
          0.0
        ],
        [
          "לי\"ש- לאומי",
          "70002- 10- לאומי",
          10,
          "AAA.IL",
          "S&P מעלות",
          "לירה שטרלינג",
          0,
          0,
          0.887533342,
          0.01,
          0.0
        ]
      ]
    },
    "תעודות התחייבות ממשלתיות": {
      "columns": [
        "שם המנפיק/שם נייר ערך",
        "מספר ני\"ע",
        "זירת מסחר",
        "דירוג",
        "שם מדרג",
        "תאריך רכישה",
        "מח\"מ",
        "סוג מטבע",
        "שיעור ריבית",
        "תשואה לפידיון",
        "ערך נקוב",
        "שער",
        "פדיון/ ריבית לקבל",
        "שווי שוק",
        "שעור מערך נקוב**** מונפק",
        "שעור מנכסי אפיק ההשקעה",
        "שעור מסך נכסי השקעה"
      ],
      "data": [
        [
          "ממשל צמודה 0418- גליל",
          1108927,
          "TASE",
          "RF",
          "",
          "16/01/18",
          0.08,
          "שקל חדש",
          3.5,
          -2.46,
          8897,
          120.43,
          0.0,
          10.7146571,
          0.0,
          0.01,
          0.0
        ],
        [
          "ממשל צמודה 0527- גליל",
          1140847,
          "TASE",
          "RF",
          "",
          "27/07/17",
          8.85,
          "שקל חדש",
          0.75,
          0.2,
          6435559,
          105.55,
          0.0,
          6792.7325245,
          0.1,
          4.77,
          2.99
        ],
        [
          "ממשל צמודה 0923- גליל",
          1128081,
          "TASE",
          "RF",
          "",
          "05/11/13",
          5.26,
          "שקל חדש",
          1.75,
          -0.26,
          11718733,
          112.7,
          0.0,
          13207.012091,
          0.08,
          9.28,
          5.82
        ],
        [
          "ממשל צמודה 1025- גליל",
          1135912,
          "TASE",
          "RF",
          "",
          "26/10/15",
          7.39,
          "שקל חדש",
          0.75,
          -0.01,
          30174787,
          105.3,
          0.0,
          31774.050711,
          0.22,
          22.34,
          14.0
        ],
        [
          "ממשלתי צמוד 1020- גליל",
          1137181,
          "TASE",
          "RF",
          "",
          "26/04/17",
          2.58,
          "שקל חדש",
          0.1,
          -0.77,
          6838640,
          102.0,
          0.0,
          6975.4128,
          0.05,
          4.9,
          3.07
        ],
        [
          "ממשל שקלית 0219- שחר",
          1110907,
          "TASE",
          "RF",
          "",
          "03/09/17",
          0.91,
          "שקל חדש",
          6.0,
          0.16,
          6250000,
          105.85,
          0.0,
          6615.625,
          0.03,
          4.65,
          2.92
        ],
        [
          "ממשל שקלית 0347- שחר",
          1140193,
          "TASE",
          "RF",
          "",
          "30/10/17",
          19.01,
          "שקל חדש",
          3.75,
          2.9,
          5417729,
          116.6,
          202.60844,
          6519.680454,
          0.12,
          4.58,
          2.87
        ],
        [
          "ממשל שקלית 0825- שחר",
          1135557,
          "TASE",
          "RF",
          "",
          "08/06/15",
          6.96,
          "שקל חדש",
          1.75,
          1.38,
          22903912,
          103.58,
          0.0,
          23723.8720496,
          0.14,
          16.68,
          10.46
        ],
        [
          "ממשל שקלית 1018- שחר",
          1136548,
          "TASE",
          "RF",
          "",
          "01/11/16",
          0.58,
          "שקל חדש",
          0.5,
          0.09,
          14513000,
          100.45,
          0.0,
          14578.3085,
          0.1,
          10.25,
          6.43
        ],
        [
          "ממשל שקלית 519- שחר",
          1131770,
          "TASE",
          "RF",
          "",
          "03/10/17",
          1.14,
          "שקל חדש",
          2.25,
          0.17,
          10000000,
          104.3,
          0.0,
          10430.0,
          0.05,
          7.33,
          4.6
        ],
        [
          "ממשלתי שקלית 0142- שחר",
          1125400,
          "TASE",
          "RF",
          "",
          "01/10/13",
          15.63,
          "שקל חדש",
          5.5,
          2.64,
          14325926,
          151.0,
          0.0,
          21632.14826,
          0.08,
          15.21,
          9.53
        ]
      ]
    },
    "אג\"ח קונצרני": {
      "columns": [
        "שם המנפיק/שם נייר ערך",
        "מספר ני\"ע",
        "זירת מסחר",
        "ספק מידע",
        "מספר מנפיק",
        "ענף מסחר",
        "דירוג",
        "שם מדרג",
        "תאריך רכישה",
        "מח\"מ",
        "סוג מטבע",
        "שיעור ריבית",
        "תשואה לפידיון",
        "ערך נקוב",
        "שער",
        "פדיון/ ריבית לקבל",
        "שווי שוק",
        "שעור מערך נקוב מונפק",
        "שעור מנכסי אפיק ההשקעה",
        "שעור מסך נכסי השקעה"
      ],
      "data": [
        [
          "בינלאומי הנפק ט- הבינלאומי הראשון הנפקות בע\"מ",
          1135177,
          "TASE",
          "אחר",
          513141879,
          "בנקים",
          "AA+.IL",
          "S&P מעלות",
          "30/03/15",
          1.99,
          "שקל חדש",
          0.8,
          -0.17,
          580000.0,
          102.36,
          4.65884,
          598.34684,
          0.09,
          3.38,
          0.26
        ],
        [
          "אמות אגח ג- אמות השקעות בע\"מ",
          1117357,
          "TASE",
          "אחר",
          520026683,
          "נדל\"ן ובינוי",
          "AA.IL",
          "S&P מעלות",
          "01/10/13",
          1.72,
          "שקל חדש",
          4.9,
          0.03,
          18900.0,
          117.53,
          0.0,
          22.21317,
          0.01,
          0.13,
          0.01
        ],
        [
          "אלוני חץ אגח ו- אלוני-חץ נכסים והשקעות בע\"מ",
          3900206,
          "TASE",
          "אחר",
          390,
          "נדל\"ן ובינוי",
          "AA-.IL",
          "S&P מעלות",
          "01/10/13",
          0.91,
          "שקל חדש",
          4.25,
          0.04,
          120404.49,
          124.57,
          0.0,
          149.987873193,
          0.06,
          0.85,
          0.07
        ],
        [
          "אלוני חץ אגח ח- אלוני-חץ נכסים והשקעות בע\"מ",
          3900271,
          "TASE",
          "אחר",
          390,
          "נדל\"ן ובינוי",
          "AA-.IL",
          "S&P מעלות",
          "01/10/13",
          2.81,
          "שקל חדש",
          4.45,
          0.45,
          310500.0,
          114.22,
          0.0,
          354.6531,
          0.06,
          2.0,
          0.16
        ],
        [
          "פתאל החזקות אגח א- פתאל החזקות 1998 בע\"מ",
          1143437,
          "TASE",
          "אחר",
          512607888,
          "מלונאות ותיירות",
          "A1.IL",
          "מידרוג",
          "27/02/18",
          2.85,
          "שקל חדש",
          3.6,
          1.76,
          470599.95,
          106.54,
          0.0,
          501.37718673,
          0.48,
          2.83,
          0.22
        ],
        [
          "אדרי-אל   אגח ב- אדרי-אל החזקות בע\"מ",
          1123371,
          "TASE",
          "אחר",
          513910091,
          "נדל\"ן ובינוי",
          "CCC.IL",
          "S&P מעלות",
          "01/10/13",
          0.27,
          "שקל חדש",
          8.0,
          20.18,
          97209.23,
          102.55,
          0.0,
          99.688065365,
          0.11,
          0.56,
          0.04
        ],
        [
          "תמר פטרוליום אגח א- תמר פטרוליום בעמ",
          1141332,
          "TASE",
          "אחר",
          515334662,
          "חיפושי נפט וגז",
          "A1.IL",
          "מידרוג",
          "19/07/17",
          5.77,
          "שקל חדש",
          4.69,
          5.77,
          628773.0,
          94.05,
          0.0,
          591.3610065,
          0.03,
          3.34,
          0.26
        ],
        [
          "TEVA 4.1 10/01/46- טבע תעשיות פרמצבטיות בע\"מ",
          "US88167AAF84",
          "אחר",
          "בלומברג",
          520013954,
          "Pharmaceuticals & Biotechnology",
          "BB",
          "S&P",
          "09/11/17",
          14.69,
          "דולר אמריקאי",
          4.1,
          6.14,
          590000.0,
          75.63022222033898,
          0.0,
          1568.0111452054,
          0.03,
          8.86,
          0.69
        ],
        [
          "BAC 3.419 12/20/28- Bank of America",
          "usu0r8a1ab34",
          "אחר",
          "בלומברג",
          10043,
          "Banks",
          "A-",
          "S&P",
          "28/12/17",
          8.95,
          "דולר אמריקאי",
          3.42,
          3.96,
          335000.0,
          96.57022501492537,
          0.0,
          1136.8150318532,
          0.01,
          6.42,
          0.5
        ],
        [
          "BAC 4% 04/01/24- Bank of America",
          "US06051GFF19",
          "אחר",
          "בלומברג",
          10043,
          "Banks",
          "A-",
          "S&P",
          "21/01/16",
          5.31,
          "דולר אמריקאי",
          4.0,
          3.61,
          77000.0,
          104.21877779220779,
          0.0,
          281.9930845746,
          0.0,
          1.59,
          0.12
        ],
        [
          "Bac 4.125  01/24- Bank of America",
          "US06051GFB05",
          "אחר",
          "בלומברג",
          10043,
          "Banks",
          "A3",
          "Moodys",
          "25/06/14",
          5.21,
          "דולר אמריקאי",
          4.13,
          3.55,
          68000.0,
          103.87270838235294,
          0.0,
          248.2059141338,
          0.0,
          1.4,
          0.11
        ],
        [
          "JPM 3.3 04/01/26- JP MORGAN",
          "US46625HQW33",
          "אחר",
          "בלומברג",
          10232,
          "Banks",
          "A-",
          "S&P",
          "31/01/18",
          6.97,
          "דולר אמריקאי",
          3.3,
          3.79,
          29000.0,
          98.4603151724138,
          0.0,
          100.3369687796,
          0.0,
          0.57,
          0.04
        ],
        [
          "JPM 3.9 07/15/25- JP MORGAN",
          "US46625HMN79",
          "אחר",
          "בלומברג",
          10232,
          "Banks",
          "A3",
          "Moodys",
          "30/07/15",
          6.38,
          "דולר אמריקאי",
          3.9,
          3.77,
          407000.0,
          101.799,
          0.0,
          1455.92726202,
          0.02,
          8.22,
          0.64
        ],
        [
          "WFC 3 02/19/25- WELLS FARGO COMPANY",
          "US94974BGH78",
          "אחר",
          "בלומברג",
          10486,
          "Banks",
          "A-",
          "S&P",
          "20/08/15",
          6.25,
          "דולר אמריקאי",
          3.0,
          3.8,
          106000.0,
          95.69416669811321,
          0.0,
          356.4454598838,
          0.0,
          2.01,
          0.16
        ],
        [
          "WFC 3 04/22/26- WELLS FARGO COMPANY",
          "US949746RW34",
          "אחר",
          "בלומברג",
          10486,
          "Banks",
          "A-",
          "S&P",
          "31/01/18",
          5.17,
          "דולר אמריקאי",
          3.0,
          7.17,
          30000.0,
          95.947096,
          0.0,
          101.1474286032,
          0.0,
          0.57,
          0.04
        ],
        [
          "WFC 3.55 09/29/25- WELLS FARGO COMPANY",
          "US94974BGP94",
          "אחר",
          "בלומברג",
          10486,
          "Banks",
          "A-",
          "S&P",
          "10/02/16",
          6.65,
          "דולר אמריקאי",
          3.55,
          3.83,
          312000.0,
          98.358,
          0.0,
          1078.36563744,
          0.01,
          6.09,
          0.48
        ],
        [
          "C 3.4 05/01/26- CITIGROUP INC",
          "US172967KN09",
          "אחר",
          "בלומברג",
          10083,
          "Banks",
          "BBB+",
          "S&P",
          "31/01/18",
          7.03,
          "דולר אמריקאי",
          3.4,
          3.9,
          31000.0,
          98.19863,
          0.0,
          106.9716956042,
          0.0,
          0.6,
          0.05
        ],
        [
          "C 3.7 12/01/2026- CITIGROUP INC",
          "US172967KG57",
          "אחר",
          "בלומברג",
          10083,
          "Banks",
          "Baa1",
          "Moodys",
          "07/01/16",
          6.79,
          "דולר אמריקאי",
          3.7,
          3.88,
          413000.0,
          99.82638888619854,
          0.0,
          1448.7624131554,
          0.02,
          8.18,
          0.64
        ],
        [
          "C 4.5% 14/01/2022- CITIGROUP INC",
          "US172967FT34",
          "אחר",
          "בלומברג",
          10083,
          "Banks",
          "Baa1",
          "Moodys",
          "01/10/13",
          3.51,
          "דולר אמריקאי",
          4.5,
          3.42,
          1000.0,
          104.7865,
          0.0,
          3.68219761,
          0.0,
          0.02,
          0.0
        ],
        [
          "Verizon 4.125% 16/03/2027- VERIZON COMMUNICATI",
          "US92343VDY74",
          "אחר",
          "בלומברג",
          10469,
          "Telecommunication Services",
          "BBB+",
          "S&P",
          "29/03/17",
          7.59,
          "דולר אמריקאי",
          4.13,
          3.96,
          262492.0,
          101.61491781082852,
          0.0,
          937.29283963084,
          0.01,
          5.29,
          0.41
        ],
        [
          "Bayer 3.75% 01/07/74- Bayer AG",
          "DE000A11QR73",
          "אחר",
          "בלומברג",
          12075,
          "Pharmaceuticals & Biotechnology",
          "BBB",
          "S&P",
          "14/07/14",
          24.51,
          "אירו",
          3.75,
          3.46,
          198000.0,
          109.80969863636363,
          0.0,
          941.18156244504,
          0.01,
          5.32,
          0.41
        ],
        [
          "Swk 5.75% 15.12.53- Stanley black & decker i",
          "US854502AF89",
          "אחר",
          "בלומברג",
          12716,
          "Capital Goods",
          "Baa2",
          "Moodys",
          "23/12/13",
          15.48,
          "דולר אמריקאי",
          5.75,
          5.69,
          117000.0,
          103.7341111111111,
          0.0,
          426.49034974,
          0.03,
          2.41,
          0.19
        ],
        [
          "Wpp LN 3.75 19/09/24",
          "US92936MAF41",
          "אחר",
          "בלומברג",
          12987,
          "Media",
          "BBB",
          "S&P",
          "01/05/16",
          5.8,
          "דולר אמריקאי",
          3.75,
          3.99,
          52000.0,
          98.90816673076922,
          0.0,
          180.7329149038,
          0.01,
          1.02,
          0.08
        ],
        [
          "PEMEX 4.5 01/26",
          "US71654QBW15",
          "אחר",
          "בלומברג",
          12345,
          "Banks",
          "Baa3",
          "Moodys",
          "29/03/16",
          6.61,
          "דולר אמריקאי",
          4.5,
          5.05,
          260000.0,
          97.628,
          0.0,
          891.9684592,
          0.02,
          5.04,
          0.39
        ],
        [
          "Petroleos mexica 3.5% 01/23- PETROLEOS MEXICANOS",
          "US71654QBG64",
          "אחר",
          "בלומברג",
          12345,
          "Energy",
          "Baa3",
          "Moodys",
          "26/06/14",
          4.46,
          "דולר אמריקאי",
          3.5,
          4.47,
          104000.0,
          96.58761115384615,
          0.0,
          352.9852202184,
          0.0,
          1.99,
          0.16
        ],
        [
          "VW 3.75% 24/03/49- Volkswagen intl fin",
          "XS1048428012",
          "אחר",
          "בלומברג",
          16302,
          "Automobiles & Components",
          "BBB-",
          "S&P",
          "30/04/14",
          19.23,
          "אירו",
          3.75,
          3.41,
          135000.0,
          106.46136985185186,
          0.0,
          622.14747004984,
          0.01,
          3.51,
          0.27
        ],
        [
          "Cielbz 3.75% 16/11/22- Cielo sa",
          "USP28610AA46",
          "אחר",
          "בלומברג",
          12830,
          "Commercial & Professional Services",
          "Ba1",
          "Moodys",
          "21/01/15",
          4.24,
          "דולר אמריקאי",
          3.75,
          4.66,
          296000.0,
          97.80116665540541,
          0.0,
          1017.2729668962,
          0.03,
          5.75,
          0.45
        ],
        [
          "PTTEPT 4 7/8 PERP- Ptt explor & product",
          "USY7150MAB38",
          "אחר",
          "בלומברג",
          12829,
          "Energy",
          "BB+",
          "S&P",
          "02/08/17",
          1.17,
          "דולר אמריקאי",
          4.88,
          4.37,
          53000.0,
          103.95042,
          0.0,
          193.5993412164,
          0.01,
          1.09,
          0.09
        ],
        [
          "BRFSBZ 4 3/4 05/22/2- BRF-BRASIL FOODS SA-ADR",
          "USP1905CAE05",
          "אחר",
          "בלומברג",
          10889,
          "Food, Beverage & Tobacco",
          "Ba2",
          "Moodys",
          "29/05/15",
          5.28,
          "דולר אמריקאי",
          4.75,
          6.31,
          278000.0,
          94.24969446043166,
          0.0,
          920.7177252084,
          0.04,
          5.2,
          0.41
        ],
        [
          "Telefonica 6.5 29/09/49- TELEFONICA S.A",
          "XS0972570351",
          "אחר",
          "בלומברג",
          10414,
          "Telecommunication Services",
          "Ba2",
          "Moodys",
          "07/02/14",
          13.92,
          "אירו",
          6.5,
          6.27,
          160000.0,
          106.3861780625,
          0.0,
          736.83918015512,
          0.01,
          4.16,
          0.32
        ],
        [
          "Oro negro dril 7.5% 2019- Oro negro dril pte ltd",
          "no0010700982",
          "אחר",
          "בלומברג",
          12824,
          "Energy",
          0,
          "לא מדורג",
          "23/12/14",
          0.82,
          "דולר אמריקאי",
          7.5,
          0.01,
          181691.0,
          43.7295,
          0.0,
          279.19631637933,
          0.03,
          1.58,
          0.12
        ]
      ]
    },
    "מניות": {
      "columns": [
        "שם המנפיק/שם נייר ערך",
        "מספר ני\"ע",
        "זירת מסחר",
        "ספק מידע",
        "מספר מנפיק",
        "ענף מסחר",
        "סוג מטבע",
        "ערך נקוב",
        "שער",
        "פדיון/ ריבית לקבל",
        "שווי שוק",
        "שעור מערך נקוב מונפק",
        "שעור מנכסי אפיק ההשקעה",
        "שעור מסך נכסי השקעה"
      ],
      "data": [
        [
          "הראל השקעות- הראל השקעות בביטוח ושרותים פיננסים בע\"מ",
          585018,
          "TASE",
          "אחר",
          520033986,
          "ביטוח",
          "שקל חדש",
          1711,
          2773.0,
          0.0,
          47.44603,
          0.0,
          0.35,
          0.02
        ],
        [
          "דיסקונט א- בנק דיסקונט לישראל בע\"מ",
          691212,
          "TASE",
          "אחר",
          520007030,
          "בנקים",
          "שקל חדש",
          74005,
          1006.0,
          0.0,
          744.4903,
          0.01,
          5.44,
          0.33
        ],
        [
          "פועלים- בנק הפועלים בע\"מ",
          662577,
          "TASE",
          "אחר",
          520000118,
          "בנקים",
          "שקל חדש",
          65416,
          2404.0,
          0.0,
          1572.60064,
          0.0,
          11.49,
          0.69
        ],
        [
          "לאומי- בנק לאומי לישראל בע\"מ",
          604611,
          "TASE",
          "אחר",
          520018078,
          "בנקים",
          "שקל חדש",
          92293,
          2111.0,
          0.0,
          1948.30523,
          0.01,
          14.23,
          0.86
        ],
        [
          "מזרחי טפחות- בנק מזרחי טפחות בע\"מ",
          695437,
          "TASE",
          "אחר",
          520000522,
          "בנקים",
          "שקל חדש",
          347,
          6703.0,
          0.0,
          23.25941,
          0.0,
          0.17,
          0.01
        ],
        [
          "בינלאומי 5- הבנק הבינלאומי הראשון לישראל בע\"מ",
          593038,
          "TASE",
          "אחר",
          520029083,
          "בנקים",
          "שקל חדש",
          6288,
          7390.0,
          0.0,
          464.6832,
          0.01,
          3.39,
          0.2
        ],
        [
          "שופרסל- שופר-סל בע\"מ",
          777037,
          "TASE",
          "אחר",
          520022732,
          "מסחר",
          "שקל חדש",
          18541,
          2233.0,
          0.0,
          414.02053,
          0.01,
          3.02,
          0.18
        ],
        [
          "אלוני חץ- אלוני-חץ נכסים והשקעות בע\"מ",
          390013,
          "TASE",
          "אחר",
          390,
          "נדל\"ן ובינוי",
          "שקל חדש",
          21162,
          3161.0,
          13.7553,
          682.68612,
          0.01,
          4.99,
          0.3
        ],
        [
          "אמות- אמות השקעות בע\"מ",
          1097278,
          "TASE",
          "אחר",
          520026683,
          "נדל\"ן ובינוי",
          "שקל חדש",
          28245,
          1878.0,
          0.0,
          530.4411,
          0.01,
          3.87,
          0.23
        ],
        [
          "גזית גלוב- גזית-גלוב בע\"מ",
          126011,
          "TASE",
          "אחר",
          520033234,
          "נדל\"ן ובינוי",
          "שקל חדש",
          8406,
          3463.0,
          0.0,
          291.09978,
          0.0,
          2.13,
          0.13
        ],
        [
          "מליסרון- מליסרון בע\"מ",
          323014,
          "TASE",
          "אחר",
          520037789,
          "נדל\"ן ובינוי",
          "שקל חדש",
          2920,
          13970.0,
          0.0,
          407.924,
          0.01,
          2.98,
          0.18
        ],
        [
          "עזריאלי קבוצה- קבוצת עזריאלי בע\"מ (לשעבר קנית מימון)",
          1119478,
          "TASE",
          "אחר",
          1420,
          "נדל\"ן ובינוי",
          "שקל חדש",
          5222,
          16810.0,
          0.0,
          877.8182,
          0.0,
          6.41,
          0.39
        ],
        [
          "אינרום- אינרום תעשיות בנייה בע\"מ",
          1132356,
          "TASE",
          "אחר",
          515001659,
          "מתכת ומוצרי בניה",
          "שקל חדש",
          18233,
          1630.0,
          0.0,
          297.1979,
          0.02,
          2.17,
          0.13
        ],
        [
          "שפיר- שפיר הנדסה ותעשיה בע\"מ",
          1133875,
          "TASE",
          "אחר",
          514892801,
          "מתכת ומוצרי בניה",
          "שקל חדש",
          32243,
          1122.0,
          5.51721,
          367.28367,
          0.01,
          2.68,
          0.16
        ],
        [
          "אשטרום נכסים- אשטרום נכסים בע\"מ",
          251017,
          "TASE",
          "אחר",
          520036617,
          "נדל\"ן ובינוי",
          "שקל חדש",
          4400,
          1692.0,
          2.53666,
          76.98466,
          0.01,
          0.56,
          0.03
        ],
        [
          "בראק קפיטל- בראק קפיטל פרופרטיז אן וי",
          1121607,
          "TASE",
          "אחר",
          34250659,
          "נדל\"ן ובינוי",
          "שקל חדש",
          150,
          41990.0,
          0.0,
          62.985,
          0.0,
          0.46,
          0.03
        ],
        [
          "גב ים- חברת גב-ים לקרקעות בע\"מ",
          759019,
          "TASE",
          "אחר",
          520001736,
          "נדל\"ן ובינוי",
          "שקל חדש",
          162,
          165900.0,
          0.0,
          268.758,
          0.01,
          1.96,
          0.12
        ],
        [
          "לוינשטיין נכסים- לוינשטיין נכסים",
          1119080,
          "TASE",
          "אחר",
          511134298,
          "נדל\"ן ובינוי",
          "שקל חדש",
          2000,
          7312.0,
          0.0,
          146.24,
          0.01,
          1.07,
          0.06
        ],
        [
          "מגדלי תיכון- מגדלי הים התיכון",
          1131523,
          "TASE",
          "אחר",
          512719485,
          "נדל\"ן ובינוי",
          "שקל חדש",
          3225,
          710.7,
          0.0,
          22.920075,
          0.0,
          0.17,
          0.01
        ],
        [
          "ריט 1- ריט 1 בע\"מ",
          1098920,
          "TASE",
          "אחר",
          513821488,
          "נדל\"ן ובינוי",
          "שקל חדש",
          9700,
          1439.0,
          0.0,
          139.583,
          0.01,
          1.02,
          0.06
        ],
        [
          "דנאל כא- דנאל (אדיר יהושע) בע\"מ",
          314013,
          "TASE",
          "אחר",
          520037565,
          "שירותים",
          "שקל חדש",
          327,
          17580.0,
          0.8175,
          58.3041,
          0.01,
          0.43,
          0.03
        ],
        [
          "מיטב דש- מיטב דש השקעות בע\"מ",
          1081843,
          "TASE",
          "אחר",
          520043795,
          "שירותים פיננסיים",
          "שקל חדש",
          2225,
          1123.0,
          0.445,
          25.43175,
          0.0,
          0.19,
          0.01
        ],
        [
          "נאוי- קבוצת האחים נאוי בע\"מ לשעבר גולדן אקוויטי",
          208017,
          "TASE",
          "אחר",
          520036070,
          "שירותים פיננסיים",
          "שקל חדש",
          1009,
          1852.0,
          0.0,
          18.68668,
          0.0,
          0.14,
          0.01
        ],
        [
          "פתאל החזקות- פתאל החזקות 1998 בע\"מ",
          1143429,
          "TASE",
          "אחר",
          512607888,
          "מלונאות ותיירות",
          "שקל חדש",
          500,
          34010.0,
          0.0,
          170.05,
          0.0,
          1.24,
          0.07
        ],
        [
          "וילאר- וילאר אינטרנשיונל בע\"מ",
          416016,
          "TASE",
          "אחר",
          520038910,
          "נדל\"ן ובינוי",
          "שקל חדש",
          6335,
          9754.0,
          0.0,
          617.9159,
          0.03,
          4.51,
          0.27
        ],
        [
          "צרפתי- צבי צרפתי השקעות ובנין (1992) בע\"מ",
          425017,
          "TASE",
          "אחר",
          520039090,
          "נדל\"ן ובינוי",
          "שקל חדש",
          21600,
          1165.0,
          0.0,
          251.64,
          0.11,
          1.84,
          0.11
        ],
        [
          "יעקובי קבוצה- קבוצת אחים יעקובי",
          1142421,
          "TASE",
          "אחר",
          514010081,
          "נדל\"ן ובינוי",
          "שקל חדש",
          18300,
          235.7,
          0.0,
          43.1331,
          0.01,
          0.32,
          0.02
        ],
        [
          "גלובל כנפיים- גלובל כנפיים ליסינג בע\"מ",
          1141316,
          "TASE",
          "אחר",
          513342444,
          "שירותים",
          "שקל חדש",
          19800,
          199.8,
          0.0,
          39.5604,
          0.02,
          0.29,
          0.02
        ],
        [
          "הולמס פלייס- הולמס פלייס אינטרנשיונל בע\"מ",
          1142587,
          "TASE",
          "אחר",
          512466723,
          "שירותים",
          "שקל חדש",
          10500,
          398.0,
          0.0,
          41.79,
          0.01,
          0.31,
          0.02
        ],
        [
          "פננטפארק- פננטפארק פלוטינג רייט קפיטל לימיטד",
          1142405,
          "TASE",
          "אחר",
          1504619,
          "שירותים פיננסיים",
          "שקל חדש",
          1982,
          4500.0,
          0.6484,
          89.8384,
          0.01,
          0.66,
          0.04
        ],
        [
          "Boeing com- BOEING CO",
          "US0970231058",
          "NYSE",
          "בלומברג",
          27015,
          "Capital Goods",
          "דולר אמריקאי",
          287,
          32788.0,
          0.0,
          330.67288184,
          0.0,
          2.42,
          0.15
        ],
        [
          "Centene Corporation- Centene Corporation",
          "US15135B1017",
          "NYSE",
          "בלומברג",
          "",
          "Health Care Equipment & Services",
          "דולר אמריקאי",
          649,
          10687.0,
          0.0,
          243.72622582,
          0.0,
          1.78,
          0.11
        ],
        [
          "Holdings plc 888- 888 Holdings plc",
          "GI000A0F6407",
          "LSE",
          "בלומברג",
          12083,
          "Hotels Restaurants & Leisure",
          "לירה שטרלינג",
          12160,
          269.8,
          0.0,
          162.207731456,
          0.0,
          1.18,
          0.07
        ],
        [
          "AFI Development Plc B- AFI Development PLC",
          "CY0101380612",
          "LSE",
          "בלומברג",
          10603,
          "Real Estate",
          "דולר אמריקאי",
          20400,
          24.6,
          0.0,
          17.6346576,
          0.0,
          0.13,
          0.01
        ],
        [
          "AROUNDTOWN SA- Aroundtown property",
          "LU1673108939",
          "FWB",
          "בלומברג",
          12853,
          "Real Estate",
          "אירו",
          9699,
          635.5,
          0.0,
          266.814873276,
          0.0,
          1.95,
          0.12
        ],
        [
          "Atrium european real estaste- Atrium european real estaste",
          "JE00B3DCF752",
          "אחר",
          "בלומברג",
          10702,
          "Real Estate",
          "אירו",
          10180,
          400.0,
          0.0,
          176.268736,
          0.0,
          1.29,
          0.08
        ],
        [
          "Globalworth Real estate- Global worth real estate invest",
          "GG00B979FD04",
          "LSE",
          "בלומברג",
          12682,
          "Real Estate",
          "אירו",
          8203,
          930.0,
          0.0,
          330.23506152,
          0.01,
          2.41,
          0.15
        ],
        [
          "Alibaba Group ho- ALIBABA COM LTD",
          "US01609W1027",
          "NYSE",
          "בלומברג",
          10825,
          "Software & Services",
          "דולר אמריקאי",
          314,
          18354.0,
          0.0,
          202.51730184,
          0.0,
          1.48,
          0.09
        ],
        [
          "BAIDU.COM ADR- Baidu.com, Inc",
          "US0567521085",
          "NASDAQ",
          "בלומברג",
          10041,
          "Software & Services",
          "דולר אמריקאי",
          250,
          22319.0,
          0.0,
          196.072415,
          0.0,
          1.43,
          0.09
        ],
        [
          "Tencent holdings- Tencent holdings",
          "KYG875721634",
          "HKSE",
          "בלומברג",
          11074,
          "Software & Services",
          "דולר הונג קונג",
          965,
          40960.0,
          0.0,
          176.4063232,
          0.0,
          1.29,
          0.08
        ],
        [
          "Samsung electronics- Samsung Electronics co ltd",
          "US7960508882",
          "LSE",
          "בלומברג",
          11111,
          "Technology Hardware & Equipment",
          "דולר אמריקאי",
          122,
          114600.0,
          0.00428708,
          491.30365508,
          0.0,
          3.59,
          0.22
        ],
        [
          "Delta Airlines inc- Delta Air Lines, Inc",
          "US2473617023",
          "NYSE",
          "בלומברג",
          27175,
          "Transportation",
          "דולר אמריקאי",
          998,
          5481.0,
          0.0,
          192.21713532,
          0.0,
          1.4,
          0.08
        ],
        [
          "Southwest Airlines- SOUTHWEST AIRLINES CO",
          "US8447411088",
          "NYSE",
          "בלומברג",
          10793,
          "Transportation",
          "דולר אמריקאי",
          805,
          5728.0,
          0.0,
          162.0319456,
          0.0,
          1.18,
          0.07
        ]
      ]
    },
    "תעודות סל": {
      "columns": [
        "שם המנפיק/שם נייר ערך",
        "מספר ני\"ע",
        "זירת מסחר",
        "מספר מנפיק",
        "ענף מסחר",
        "סוג מטבע",
        "ערך נקוב",
        "שער",
        "פדיון/ ריבית לקבל",
        "שווי שוק",
        "שעור מערך נקוב מונפק",
        "שעור מנכסי אפיק ההשקעה",
        "שעור מסך נכסי השקעה"
      ],
      "data": [
        [
          "Ishares dax- DAXEX FUND",
          "DE0005933931",
          "אחר",
          20001,
          "מניות",
          "אירו",
          1430,
          10484,
          0,
          648.97889056,
          0,
          29.12,
          0.29
        ],
        [
          "Ishares m .hong kong- ISHARES M.HONG KONG",
          "US4642868719",
          "NYSE",
          20056,
          "מניות",
          "דולר אמריקאי",
          2910,
          2531,
          0,
          258.8134794,
          0,
          11.61,
          0.11
        ],
        [
          "Ishares mcsi australia- ISHARES MSCI AUSTRALIA",
          "us4642861037",
          "NYSE",
          20064,
          "מניות",
          "דולר אמריקאי",
          5220,
          2202,
          0,
          403.9146216,
          0,
          18.13,
          0.18
        ],
        [
          "Powershares  QQQ NAS1- POWERSHARES",
          "US73935A1043",
          "NASDAQ",
          10339,
          "מניות",
          "דולר אמריקאי",
          420,
          16013,
          0,
          236.3326644,
          0,
          10.61,
          0.1
        ],
        [
          "Energy s.sector spdr- SPDR - State Street Global Advisors",
          "US81369Y5069",
          "NYSE",
          22040,
          "מניות",
          "דולר אמריקאי",
          1779,
          6741,
          0,
          421.40727846,
          0,
          18.91,
          0.19
        ],
        [
          "Spdr s&p 500 etf trust- SPDR - State Street Global Advisors",
          "US78462F1030",
          "NYSE",
          22040,
          "מניות",
          "דולר אמריקאי",
          280,
          26315,
          0,
          258.918548,
          0,
          11.62,
          0.11
        ]
      ]
    },
    "קרנות נאמנות": {
      "columns": [
        "שם המנפיק/שם נייר ערך",
        "מספר ני\"ע",
        "זירת מסחר",
        "מספר מנפיק",
        "ענף מסחר",
        "דירוג",
        "שם מדרג",
        "סוג מטבע",
        "ערך נקוב",
        "שער",
        "שווי שוק",
        "שעור מערך נקוב מונפק",
        "שעור מנכסי אפיק ההשקעה",
        "שעור מסך נכסי השקעה"
      ],
      "data": [
        [
          "*אלטשולר יתר 40 דיב ק.נ- אלטשולר שחם בית השקעות בע\"מ",
          5105903,
          "TASE",
          513862581,
          "מניות",
          0,
          "לא מדורג",
          "שקל חדש",
          38300.0,
          367.28,
          140.66824,
          0.03,
          4.78,
          0.06
        ],
        [
          "Angsana Bond Fund- Nutrimenta Singapore pte ltd",
          "IE00BNN82M77",
          "אחר",
          12789,
          "אג\"ח",
          0,
          "לא מדורג",
          "דולר אמריקאי",
          1036.31,
          14748.0,
          537.0621857832,
          0.11,
          18.24,
          0.24
        ],
        [
          "EDR fund emerging bonds- Edmond De Rothschild",
          "lu1160351620",
          "אחר",
          513872440,
          "אג\"ח",
          0,
          "לא מדורג",
          "דולר אמריקאי",
          1434.69,
          12647.0,
          637.5985884702,
          0.07,
          21.66,
          0.28
        ],
        [
          "$Gemway -Gemequity-S- Gemequity",
          "FR0013246444",
          "אחר",
          12715,
          "מניות",
          0,
          "לא מדורג",
          "דולר אמריקאי",
          68.0,
          133238.0,
          318.37486576,
          0.02,
          10.82,
          0.14
        ],
        [
          "Comgest Growth euro- Comgest",
          "ie00bhwqnn83",
          "אחר",
          12656,
          "מניות",
          0,
          "לא מדורג",
          "אירו",
          1170.0,
          3356.0,
          169.97119776,
          0.01,
          5.77,
          0.07
        ],
        [
          "EDG-US L G-I$D- Edgewood L select",
          "LU0952587862",
          "אחר",
          13050,
          "מניות",
          0,
          "לא מדורג",
          "דולר אמריקאי",
          650.0,
          21030.0,
          480.34623,
          0.0,
          16.32,
          0.21
        ],
        [
          "Hbm Healthcare- HBM Healthcare Investment ag",
          "CH0012627250",
          "אחר",
          13052,
          "מניות",
          0,
          "לא מדורג",
          "פרנק שווצרי",
          206.0,
          14400.0,
          109.000368,
          0.0,
          3.7,
          0.05
        ],
        [
          "KOT-IND MID-J- Kotak",
          "LU0675383409",
          "אחר",
          12688,
          "מניות",
          0,
          "לא מדורג",
          "דולר אמריקאי",
          7020.71,
          1747.97,
          431.237744718718,
          0.02,
          14.65,
          0.19
        ],
        [
          "L1 capital australian equities- L1 Capital Australian Equities",
          "AU60LCP00016",
          "אחר",
          27320,
          "מניות",
          0,
          "לא מדורג",
          "דולר אוסטרלי",
          26038.18,
          169.78000000000057,
          119.3561586486,
          0.0,
          4.05,
          0.05
        ]
      ]
    },
    "אופציות": {
      "columns": [
        "שם המנפיק/שם נייר ערך",
        "מספר ני\"ע",
        "זירת מסחר",
        "ענף מסחר",
        "סוג מטבע",
        "ערך נקוב",
        "שער",
        "שווי שוק",
        "שעור מערך נקוב מונפק",
        "שעור מנכסי אפיק ההשקעה",
        "שעור מסך נכסי השקעה"
      ],
      "data": [
        [
          "תC001530M803-35- מסלקת הבורסה",
          82241787,
          "TASE",
          "ל.ר.",
          "שקל חדש",
          5,
          100,
          0.005,
          0,
          2.24,
          0
        ],
        [
          "SPX C2850 20/04/18- SPX",
          70227830,
          "אחר",
          "Other",
          "דולר אמריקאי",
          1,
          9000,
          0.31626,
          0,
          141.9,
          0
        ],
        [
          "SPX C2930 20/04/18- SPX",
          70227566,
          "אחר",
          "Other",
          "דולר אמריקאי",
          -1,
          2800,
          -0.098392,
          0,
          -44.15,
          0
        ]
      ]
    },
    "חוזים עתידיים": {
      "columns": [
        "שם המנפיק/שם נייר ערך",
        "מספר ני\"ע",
        "זירת מסחר",
        "ענף מסחר",
        "סוג מטבע",
        "ערך נקוב",
        "שער",
        "שווי שוק",
        "שעור מנכסי אפיק ההשקעה",
        "שעור מסך נכסי השקעה",
        "ASX",
        "אוסטרליה",
        "בנקים וחברות אחזקה",
        "untitled1",
        "אירו"
      ],
      "data": [
        [
          "ESM8_S&P500 mini JUN18- חוזים עתידיים בחול",
          70480033,
          "אחר",
          "Other",
          "דולר אמריקאי",
          10,
          -729249.9999999972,
          -256.258449999999,
          26.3,
          -0.11,
          "",
          "",
          "",
          "שירותים",
          ""
        ],
        [
          "GXM8_dax  fut Jun18- חוזים עתידיים בחול",
          70499264,
          "אחר",
          "Other",
          "אירו",
          2,
          -739374.9999999988,
          -64.0121299999999,
          6.57,
          -0.03,
          "",
          "",
          "",
          "שירותים פיננסיים",
          ""
        ],
        [
          "HIJ8_hang sang fut 042018- חוזים עתידיים בחול",
          70570213,
          "אחר",
          "Other",
          "דולר הונג קונג",
          2,
          -1505215.9999999776,
          -13.4355580159998,
          1.38,
          -0.01,
          "",
          "",
          "",
          "תוכנה ואינטרנט",
          ""
        ],
        [
          "NQM8_nasdaq100 mini fut Jun18- חוזים עתידיים בחול",
          70489141,
          "אחר",
          "Other",
          "דולר אמריקאי",
          3,
          -1060699.036,
          -111.81889237512,
          11.48,
          -0.05,
          "",
          "",
          "",
          "תיירות ומלונות",
          ""
        ],
        [
          "TUM8- חוזים עתידיים בחול",
          70665799,
          "אחר",
          "Other",
          "דולר אמריקאי",
          16,
          1568.6000000015456,
          0.881929664000869,
          -0.09,
          0.0,
          "",
          "",
          "",
          "תעשייה שונות",
          ""
        ],
        [
          "USM8_Us long Bond (cbt_Jun18- חוזים עתידיים בחול",
          70536842,
          "אחר",
          "Other",
          "דולר אמריקאי",
          -45,
          324173.7,
          -512.61587181,
          52.61,
          -0.23,
          "",
          "",
          "",
          "תקשורת ומדיה",
          ""
        ],
        [
          "XPM8_spi 200 fut Jun18- חוזים עתידיים בחול",
          70645684,
          "אחר",
          "Other",
          "דולר אוסטרלי",
          1,
          -635000.0,
          -17.144365,
          1.76,
          -0.01,
          "",
          "",
          "",
          "אחר",
          ""
        ]
      ]
    },
    "לא סחיר - אג\"ח קונצרני": {
      "columns": [
        "שם המנפיק/שם נייר ערך",
        "מספר ני\"ע",
        "ספק המידע",
        "מספר מנפיק",
        "ענף מסחר",
        "דירוג",
        "שם מדרג",
        "תאריך רכישה",
        "מח\"מ",
        "סוג מטבע",
        "שיעור ריבית",
        "תשואה לפידיון",
        "ערך נקוב",
        "שער",
        "שווי הוגן",
        "שעור מערך נקוב מונפק",
        "שעור מנכסי אפיק ההשקעה",
        "שעור מסך נכסי השקעה"
      ],
      "data": [
        [
          "מקורות אגח 6 רמ- מקורות חברת מים בע\"מ",
          1100908,
          "אחר",
          520010869,
          "שירותים",
          "AAA.IL",
          "S&P מעלות",
          "01/10/13",
          9.02,
          "שקל חדש",
          4.9,
          1.39,
          263000.0,
          161.74,
          425.3762,
          0.01,
          2.34,
          0.19
        ],
        [
          "מקורות אגח 8 רמ- מקורות חברת מים בע\"מ",
          1124346,
          "אחר",
          520010869,
          "שירותים",
          "AAA.IL",
          "S&P מעלות",
          "01/10/13",
          11.68,
          "שקל חדש",
          4.1,
          2.25,
          3754757.69,
          128.4,
          4821.10887396,
          0.1,
          26.55,
          2.12
        ],
        [
          "חשמל צמוד 2022 רמ- חברת החשמל לישראל בע\"מ",
          6000129,
          "אחר",
          520000472,
          "חשמל",
          "Aa2.IL",
          "מידרוג",
          "01/10/13",
          3.27,
          "שקל חדש",
          6.0,
          0.41,
          7169000.0,
          126.03,
          9035.0907,
          0.19,
          49.75,
          3.98
        ],
        [
          "נתיבי גז אג\"ח א - רמ- נתיבי הגז הטבעי לישראל בע\"מ",
          1103084,
          "אחר",
          513436394,
          "שירותים",
          "AA.IL",
          "S&P מעלות",
          "01/10/13",
          4.62,
          "שקל חדש",
          5.6,
          0.5,
          1008760.14,
          151.36,
          1526.859347904,
          0.11,
          8.41,
          0.67
        ],
        [
          "נתיבי הגז אגח ד -רמ- נתיבי הגז הטבעי לישראל בע\"מ",
          1131994,
          "אחר",
          513436394,
          "שירותים",
          "AA.IL",
          "S&P מעלות",
          "28/04/14",
          10.2,
          "שקל חדש",
          2.95,
          1.46,
          112000.0,
          116.81,
          130.8272,
          0.01,
          0.72,
          0.06
        ],
        [
          "מתם מרכז תעשיות מדע חיפה אגח א לס- מת\"ם - מרכז תעשיות מדע חיפה בע\"מ",
          1138999,
          "אחר",
          510687403,
          "נדל\"ן ובינוי",
          "Aa2.IL",
          "מידרוג",
          "16/08/16",
          5.76,
          "שקל חדש",
          3.1,
          2.41,
          884450.0,
          104.89,
          927.699605,
          0.23,
          5.11,
          0.41
        ],
        [
          "אליהו הנפ אגח א לס- אליהו הנפקות בע\"מ",
          1142009,
          "אחר",
          515703528,
          "השקעה ואחזקות",
          "A1.IL",
          "מידרוג",
          "19/09/17",
          5.1,
          "שקל חדש",
          3.85,
          4.0,
          1085000.0,
          99.51,
          1079.6835,
          0.08,
          5.94,
          0.48
        ],
        [
          "ביטוח ישיר אגח יא- ביטוח ישיר - השקעות פיננסיות בע\"מ",
          1138825,
          "אחר",
          520044439,
          "השקעה ואחזקות",
          "A2.IL",
          "מידרוג",
          "21/07/16",
          5.45,
          "שקל חדש",
          4.6,
          3.22,
          197400.0,
          108.85,
          214.8699,
          0.03,
          1.18,
          0.09
        ]
      ]
    },
    "לא סחיר - מניות": {
      "columns": [
        "שם המנפיק/שם נייר ערך",
        "מספר ני\"ע",
        "ספק המידע",
        "מספר מנפיק",
        "ענף מסחר",
        "סוג מטבע",
        "ערך נקוב",
        "שער",
        "שווי הוגן",
        "שעור מערך נקוב מונפק",
        "שעור מנכסי אפיק ההשקעה",
        "שעור מסך נכסי השקעה"
      ],
      "data": [
        [
          "נארה מדיקל סנטר בע\"מ- נארה מדיקל סנטר בע\"מ",
          29992737,
          "אחר",
          515138584,
          "Health Care Equipment & Services",
          "שקל חדש",
          27.29,
          83677.308,
          22.8355373532,
          0.01,
          1.81,
          0.01
        ],
        [
          "Kougar B Shares- Feldsrasse Die Erste GmBH",
          29991613,
          "אחר",
          152554,
          "Real Estate",
          "אירו",
          26.0,
          0.0001,
          1.125488e-07,
          0.02,
          0.0,
          0.0
        ],
        [
          "דן בוש FL  Randy BV- FL RANDY BV",
          299926600,
          "אחר",
          12947,
          "Real Estate",
          "אירו",
          24.0,
          301836.735,
          313.58180603232,
          0.24,
          24.83,
          0.14
        ],
        [
          "Project Home Hema Retail- HDR AS 1 s.a.r.l",
          29992735,
          "אחר",
          13034,
          "Real Estate",
          "אירו",
          33.67,
          261469.2,
          381.093178825632,
          0.04,
          30.17,
          0.17
        ],
        [
          "Hema אמסטרדם- MMZ Properties Den Bosch Adam One BV",
          299930161,
          "אחר",
          12891,
          "Real Estate",
          "אירו",
          1006.0,
          11813.561,
          514.453741139408,
          0.04,
          40.73,
          0.23
        ],
        [
          "Energy Vision Limited- Energy Vision",
          29992742,
          "אחר",
          13038,
          "Utilities",
          "דולר אמריקאי",
          97.87,
          9044.344,
          31.1048719474192,
          0.01,
          2.46,
          0.01
        ]
      ]
    },
    "לא סחיר - קרנות השקעה": {
      "columns": [
        "שם המנפיק/שם נייר ערך",
        "מספר ני\"ע",
        "סוג מטבע",
        "תאריך רכישה",
        "ערך נקוב",
        "שער",
        "שווי הוגן",
        "שעור מערך נקוב מונפק",
        "שעור מנכסי אפיק ההשקעה",
        "שעור מסך נכסי השקעה"
      ],
      "data": [
        [
          "Magma Venture Capital iv lp- Magma Venture Capital",
          29992287,
          "דולר אמריקאי",
          "12/01/15",
          48600.0,
          125.072,
          213.598461888,
          0.05,
          2.81,
          0.09
        ],
        [
          "Stage one 3- stage one1",
          29992953,
          "דולר אמריקאי",
          "16/01/18",
          236.36,
          100.0,
          0.83056904,
          0.0,
          0.01,
          0.0
        ],
        [
          "Stage One II- stage one1",
          29993017,
          "דולר אמריקאי",
          "25/06/15",
          5349.0,
          137.93,
          25.9258552098,
          0.02,
          0.34,
          0.01
        ],
        [
          "State of mind ventures limited partnership- STATE OF MIND VENTURES LIMITED PARTNERSHIP",
          29992699,
          "דולר אמריקאי",
          "25/05/16",
          9377.0,
          147.74,
          48.6814794172,
          0.02,
          0.64,
          0.02
        ],
        [
          "Vintage Investment Partners VII- Vintage Venture",
          29992231,
          "דולר אמריקאי",
          "27/08/14",
          46006.0,
          110.29,
          178.3004211436,
          0.04,
          2.34,
          0.08
        ],
        [
          "Pontifax IV- פונטיפקס 2 שירותי ניהול הקרן (2007) בע\"מ",
          29992637,
          "דולר אמריקאי",
          "14/10/15",
          7200.0,
          109.61481,
          27.73342384848,
          0.01,
          0.36,
          0.01
        ],
        [
          "פונטיפקס V- פונטיפקס 2 שירותי ניהול הקרן (2007) בע\"מ",
          29992982,
          "דולר אמריקאי",
          "22/03/18",
          2750.0,
          100.0,
          9.6635,
          0.0,
          0.13,
          0.0
        ],
        [
          "קרן ריאלטי 2- ריאליטי קרן השקעות",
          9840800,
          "דולר אמריקאי",
          "01/10/13",
          35439.0,
          126.64,
          157.7081428944,
          0.09,
          2.07,
          0.07
        ],
        [
          "נדל\"ן נווה אילן- ריאליטי קרן השקעות",
          29992309,
          "שקל חדש",
          "23/02/15",
          253166.0,
          114.078,
          288.80670948,
          0.2,
          3.8,
          0.13
        ],
        [
          "Glilot 1 co-invest fund- Glilot Capital investments",
          29992687,
          "דולר אמריקאי",
          "13/04/16",
          953.0,
          134.43,
          4.5018483006,
          0.03,
          0.06,
          0.0
        ],
        [
          "Klirmark Opportunity fund II- Klirmark Opportunity L.P",
          29992297,
          "שקל חדש",
          "01/02/15",
          166895.0,
          142.82323,
          238.3648297085,
          0.03,
          3.13,
          0.11
        ],
        [
          "Reality Real Estate Investment Fund 3 L.P- Reality Real Estate Investment Fund 3 L.P",
          29992353,
          "שקל חדש",
          "30/06/15",
          278567.0,
          103.703,
          288.88233601,
          0.08,
          3.8,
          0.13
        ],
        [
          "יסודות א נדלן ופיתוח אנקס 1 שותפות מוגבלת- יסודות א נדלן שותפות מוגבלת",
          29992728,
          "שקל חדש",
          "09/11/16",
          173360.0,
          111.03268,
          192.486254048,
          0.15,
          2.53,
          0.08
        ],
        [
          "קרן יסודות נדלן  ב- יסודות א נדלן שותפות מוגבלת",
          29992954,
          "שקל חדש",
          "25/01/18",
          37915.43,
          100.0,
          37.91543,
          0.0,
          0.5,
          0.02
        ],
        [
          "פנינסולה קרן צמיחה לעסקים בינונים שותפות מוגבלת- פנינסולה ניהול קרנות בע\"מ",
          29992713,
          "שקל חדש",
          "25/08/16",
          27685.41,
          95.413363,
          26.4155807413383,
          0.02,
          0.35,
          0.01
        ],
        [
          "קוגיטו קפיטל אס.אם.אי שותפות מוגבלת- קוגיטו קפיטל",
          29992707,
          "שקל חדש",
          "18/07/16",
          21227.0,
          98.306,
          20.86741462,
          0.02,
          0.27,
          0.01
        ],
        [
          "קוגיטו קפיטל בי.אמ.אי משלימה- קוגיטו קפיטל",
          29992793,
          "שקל חדש",
          "03/09/17",
          11785.0,
          103.738,
          12.2255233,
          0.02,
          0.16,
          0.01
        ],
        [
          "קרן יסודות 1- קרן יסודות 1",
          29992351,
          "שקל חדש",
          "09/06/15",
          276104.0,
          124.68402,
          344.2575665808,
          0.09,
          4.52,
          0.15
        ],
        [
          "Noy 2 Infrastructure and Energy Investments Fund- קרן נוי 1 להשקעה בתשתיות אנרגיה ש.מ",
          29992358,
          "שקל חדש",
          "02/07/15",
          344473.93,
          97.04,
          334.277501672,
          0.26,
          4.39,
          0.15
        ],
        [
          "Noy negev energy limited partnership- קרן נוי 1 להשקעה בתשתיות אנרגיה ש.מ",
          29992710,
          "שקל חדש",
          "04/08/16",
          110542.0,
          115.49301,
          127.6682831142,
          0.04,
          1.68,
          0.06
        ],
        [
          "נוי כוכב הירדן- קרן נוי 1 להשקעה בתשתיות אנרגיה ש.מ",
          29992808,
          "שקל חדש",
          "30/11/17",
          33451.0,
          102.815,
          34.39264565,
          0.03,
          0.45,
          0.02
        ],
        [
          "קרן נוי 1 להשקעה בתשתיות אנרג- קרן נוי 1 להשקעה בתשתיות אנרגיה ש.מ",
          29991682,
          "שקל חדש",
          "01/10/13",
          103842.0,
          135.055,
          140.2438131,
          0.01,
          1.84,
          0.06
        ],
        [
          "קרן תשתיות לישראל II ש.מ- קרן תשתיות ישראל",
          29991728,
          "דולר אמריקאי",
          "01/10/13",
          34283.0,
          156.908,
          189.02779251496,
          0.02,
          2.48,
          0.08
        ],
        [
          "Qumra Capital 1- Qumra Capital1",
          29992316,
          "דולר אמריקאי",
          "10/03/15",
          50054.0,
          125.25461000000023,
          220.310027907752,
          0.05,
          2.9,
          0.1
        ],
        [
          "Aurum Isis fund institutional Iti dollar- Aurum Isis Fund",
          299927080,
          "דולר אמריקאי",
          "18/09/16",
          38.0,
          109217.09,
          145.8397646188,
          0.0,
          1.92,
          0.06
        ],
        [
          "BK opportunity 3- BK Opportunities fund",
          299923780,
          "דולר אמריקאי",
          "29/02/16",
          32.0,
          105637.0,
          118.78669376,
          0.06,
          1.56,
          0.05
        ],
        [
          "BK opportunity 4- BK Opportunities fund",
          29992769,
          "דולר אמריקאי",
          "24/04/17",
          70039.22,
          110.50530599999985,
          271.97324909488,
          0.12,
          3.57,
          0.12
        ],
        [
          "Blackrock european hedge fund limitited- class I- Blackrock european hedge fund",
          299927230,
          "אירו",
          "10/11/16",
          83.31,
          27121.743999999995,
          97.8097767814003,
          0.0,
          1.29,
          0.04
        ],
        [
          "BSP Absolute Return Fund of Funds Ltd. (Class GL)- BSP ABSOLUTE RETURN FOF AI",
          "KYG166512114",
          "דולר אמריקאי",
          "24/03/14",
          119000.0,
          112.17,
          469.0568022,
          0.06,
          6.16,
          0.21
        ],
        [
          "Perceptive Life Sciences Offshore fund ltd- Perceptive",
          299927210,
          "דולר אמריקאי",
          "30/11/16",
          9.29,
          227328.02430000005,
          74.2113699295496,
          0.0,
          0.98,
          0.03
        ],
        [
          "קרן גידורPI- PI",
          299927040,
          "דולר אמריקאי",
          "11/09/16",
          55.0,
          102451.683,
          198.0083677341,
          0.01,
          2.6,
          0.09
        ],
        [
          "דנמרק IPDS P/S- דנמרק IPDS P/S",
          29992180,
          "כתר דני",
          "02/04/14",
          113524.0,
          117.49115,
          77.4674833355808,
          0.05,
          1.02,
          0.03
        ],
        [
          "Investcorp Special Opportunities Italian- Investcorp Investment Advisers Limited",
          29992801,
          "אירו",
          "30/10/17",
          36020.26,
          100.0,
          155.924501488,
          0.05,
          2.05,
          0.07
        ],
        [
          "Anacap credit opportunities III- AnaCap Credit Opportunities GP III, L.P",
          29992706,
          "אירו",
          "11/07/16",
          12678.78,
          155.855,
          85.5393068086872,
          0.01,
          1.12,
          0.04
        ],
        [
          "Ares special situations fund IV- Ares special situation fund IB",
          29992320,
          "דולר אמריקאי",
          "19/03/15",
          147000.39,
          80.51199999999996,
          415.892280344755,
          0.02,
          5.47,
          0.18
        ],
        [
          "Avenue Europe fund 3- Avenue Cpital Group",
          29992670,
          "אירו",
          "27/01/16",
          95297.0,
          112.047,
          462.218137209192,
          0.04,
          6.07,
          0.2
        ],
        [
          "Avenue Europe II Fund- Avenue Cpital Group",
          29991804,
          "דולר אמריקאי",
          "01/10/13",
          14347.0,
          282.7236799999992,
          142.536155422774,
          0.0,
          1.87,
          0.06
        ],
        [
          "Crescent mezzanine parners VII- Crescent mezzanine partners",
          29992743,
          "דולר אמריקאי",
          "08/02/17",
          16100.0,
          93.318,
          52.795031772,
          0.0,
          0.69,
          0.02
        ],
        [
          "Forma Fund I l.p- Forma Fund",
          29992780,
          "אירו",
          "14/06/17",
          29678.35,
          94.26886999999978,
          121.108764693647,
          0.05,
          1.59,
          0.05
        ],
        [
          "Gatewood Capital Opportunity Fund (Cayman) LP- Gatewood Capital Opportunity Fund",
          29992724,
          "דולר אמריקאי",
          "13/10/16",
          3313.23,
          93.8,
          10.92084342636,
          0.01,
          0.14,
          0.0
        ],
        [
          "ICG Asia Pacific Fund III- ICG Fund",
          29993018,
          "דולר אמריקאי",
          "11/01/16",
          37877.67,
          116.42596000000012,
          154.965435403886,
          0.02,
          2.04,
          0.07
        ],
        [
          "ICG FUND L.P- ICG Fund",
          29992232,
          "דולר אמריקאי",
          "28/08/14",
          77086.97,
          90.17,
          244.255753463386,
          0.01,
          3.21,
          0.11
        ],
        [
          "ICG Strategic Secondaries Fund II- ICG Fund",
          29992777,
          "דולר אמריקאי",
          "07/06/17",
          5975.0,
          169.145,
          35.5139379175,
          0.0,
          0.47,
          0.02
        ],
        [
          "Kreos capital V (expert fund) LP- Kreos capital V",
          29992663,
          "אירו",
          "04/01/16",
          50262.56,
          104.86318999999995,
          228.157731709355,
          0.02,
          3.0,
          0.1
        ],
        [
          "Mideal Partnership LP- Mideal Partnership Lp",
          29992746,
          "אירו",
          "16/02/17",
          26092.0,
          98.30382000000024,
          111.031264334095,
          0.02,
          1.46,
          0.05
        ],
        [
          "Precepetive Credit Opportunities Fund ltd- Perceptive",
          29992730,
          "דולר אמריקאי",
          "21/11/16",
          39972.46,
          102.5255499999997,
          144.010693404844,
          0.08,
          1.89,
          0.06
        ],
        [
          "Signal Real Estate Opporyunities Fund- Signal Real Estate Opportunities Fund",
          29992791,
          "אירו",
          "09/08/17",
          59471.61,
          117.92000000000016,
          303.574079769946,
          0.02,
          3.99,
          0.13
        ],
        [
          "Noy Waste to energy 2 limited partnership- קרן נוי 1 להשקעה בתשתיות אנרגיה ש.מ",
          29992664,
          "לירה שטרלינג",
          "13/01/16",
          15974.0,
          113.77035,
          89.8542874404378,
          0.04,
          1.18,
          0.04
        ],
        [
          "Noy waste to energy lp- קרן נוי 1 להשקעה בתשתיות אנרגיה ש.מ",
          29992357,
          "לירה שטרלינג",
          "02/07/15",
          38745.15,
          122.43158999999999,
          234.534570246262,
          0.11,
          3.08,
          0.1
        ]
      ]
    },
    "לא סחיר - כתבי אופציה": {
      "columns": [
        "שם המנפיק/שם נייר ערך",
        "מספר ני\"ע",
        "ענף מסחר",
        "סוג מטבע",
        "תאריך רכישה",
        "ערך נקוב",
        "שער",
        "שווי הוגן",
        "שעור מערך נקוב מונפק",
        "שעור מנכסי אפיק ההשקעה",
        "שעור מסך נכסי השקעה"
      ],
      "data": [
        [
          "אליהו כתב אופ 1- אליהו חברה לביטוח",
          299927950,
          "השקעה ואחזקות",
          "שקל חדש",
          "28/09/17",
          44485.0,
          24.05,
          10.6986425,
          0.0,
          13.53,
          0.0
        ],
        [
          "אליהו כתב אופ 2- אליהו חברה לביטוח",
          299927960,
          "השקעה ואחזקות",
          "שקל חדש",
          "28/09/17",
          44485.0,
          37.48,
          16.672978,
          0.0,
          21.08,
          0.01
        ],
        [
          "אליהו כתב אופ 3- אליהו חברה לביטוח",
          299927970,
          "השקעה ואחזקות",
          "שקל חדש",
          "28/09/17",
          44485.0,
          49.02,
          21.806547,
          0.0,
          27.57,
          0.01
        ],
        [
          "כתב אופציה VW- Volkswagen intl fin",
          29992094,
          "Automobiles & Components",
          "אירו",
          "01/10/13",
          2201.1,
          292.18,
          27.839265924624,
          0.0,
          35.2,
          0.01
        ],
        [
          "אופציה סדרה A על GDR AFID- AFI Development PLC",
          29992719,
          "Real Estate",
          "דולר אמריקאי",
          "25/09/16",
          4328.4,
          7.07,
          1.07534683032,
          0.01,
          1.36,
          0.0
        ],
        [
          "אופציה סדרה B על AFRB- AFI Development PLC",
          29992720,
          "Real Estate",
          "דולר אמריקאי",
          "25/09/16",
          4403.31,
          6.0426,
          0.93498547695084,
          0.01,
          1.18,
          0.0
        ],
        [
          "כתב אופציה Kougar- Feldsrasse Die Erste GmBH",
          29991612,
          "Real Estate",
          "אירו",
          "01/10/13",
          0.8,
          1915.0,
          0.066317216,
          0.0,
          0.08,
          0.0
        ]
      ]
    },
    "לא סחיר - אופציות": {
      "columns": [
        "שם המנפיק/שם נייר ערך",
        "מספר ני\"ע",
        "ענף מסחר",
        "סוג מטבע",
        "תאריך רכישה",
        "ערך נקוב",
        "שער",
        "שווי הוגן",
        "שעור מערך נקוב מונפק",
        "שעור מנכסי אפיק ההשקעה",
        "שעור מסך נכסי השקעה"
      ],
      "data": [
        [
          "אופציה לס דולר שקל C345 06/18- חוזים סחירים ואופציות בישראל",
          29992957,
          "אחר",
          "דולר אמריקאי",
          "05/02/18",
          -190000,
          2.02770172,
          -13.538153303752,
          0,
          -19.36,
          -0.01
        ],
        [
          "אופציה לס דולר שקל C345 07/18- חוזים סחירים ואופציות בישראל",
          29992959,
          "אחר",
          "דולר אמריקאי",
          "06/02/18",
          -190000,
          2.09935504,
          -14.016553860064,
          0,
          -20.04,
          -0.01
        ],
        [
          "אופציה לס דולר שקל C345 08/18- חוזים סחירים ואופציות בישראל",
          29992967,
          "אחר",
          "דולר אמריקאי",
          "07/02/18",
          -190000,
          2.1751537,
          -14.52263119342,
          0,
          -20.76,
          -0.01
        ],
        [
          "אופציה לס דולר שקל C350 10/18- חוזים סחירים ואופציות בישראל",
          29992970,
          "אחר",
          "דולר אמריקאי",
          "08/02/18",
          -190000,
          1.67182718,
          -11.162121349988,
          0,
          -15.96,
          0.0
        ],
        [
          "אופציה לס דולר שקל C350 11/18- חוזים סחירים ואופציות בישראל",
          29992983,
          "אחר",
          "דולר אמריקאי",
          "28/03/18",
          -180000,
          1.7372419,
          -1.31084646588,
          0,
          -1.87,
          0.0
        ],
        [
          "אופציה לס דולר שקל C355 04/18- חוזים סחירים ואופציות בישראל",
          29992815,
          "אחר",
          "דולר אמריקאי",
          "13/12/17",
          -205000,
          0.3091127066038439,
          -2.22675520456211,
          0,
          -3.18,
          0.0
        ],
        [
          "אופציה לס דולר שקל C360 06/18- חוזים סחירים ואופציות בישראל",
          29992958,
          "אחר",
          "דולר אמריקאי",
          "05/02/18",
          760000,
          0.46458053,
          12.407273466392,
          0,
          17.74,
          0.01
        ],
        [
          "אופציה לס דולר שקל C360 07/18- חוזים סחירים ואופציות בישראל",
          29992960,
          "אחר",
          "דולר אמריקאי",
          "06/02/18",
          760000,
          0.589718435,
          15.749256412484,
          0,
          22.52,
          0.01
        ],
        [
          "אופציה לס דולר שקל C360 08/18- חוזים סחירים ואופציות בישראל",
          29992968,
          "אחר",
          "דולר אמריקאי",
          "07/02/18",
          760000,
          0.719848275,
          19.22455597146,
          0,
          27.49,
          0.01
        ],
        [
          "אופציה לס דולר שקל C370 11/18- חוזים סחירים ואופציות בישראל",
          29992984,
          "אחר",
          "דולר אמריקאי",
          "28/03/18",
          720000,
          0.57775673,
          0.702267474384,
          0,
          1.0,
          0.0
        ],
        [
          "אופציה לס דולר שקל C375 10/18- חוזים סחירים ואופציות בישראל",
          29992971,
          "אחר",
          "דולר אמריקאי",
          "08/02/18",
          1900000,
          0.382219862,
          25.519291306292,
          0,
          36.49,
          0.01
        ],
        [
          "אופציה לס דולר שקל P335 07/18- חוזים סחירים ואופציות בישראל",
          29992961,
          "אחר",
          "דולר אמריקאי",
          "06/02/18",
          760000,
          0.28302714,
          7.558636011696,
          0,
          10.81,
          0.0
        ],
        [
          "אופציה לס דולר שקל P335 08/18- חוזים סחירים ואופציות בישראל",
          29992969,
          "אחר",
          "דולר אמריקאי",
          "07/02/18",
          760000,
          0.44990942,
          12.015460934288,
          0,
          17.18,
          0.01
        ],
        [
          "אופציה לס דולר שקל P335 11/18- חוזים סחירים ואופציות בישראל",
          29992985,
          "אחר",
          "דולר אמריקאי",
          "28/03/18",
          720000,
          0.895679195,
          -6.181511823144,
          0,
          -8.84,
          0.0
        ],
        [
          "אופציה לס דולר שקל P340 10/18- חוזים סחירים ואופציות בישראל",
          29992972,
          "אחר",
          "דולר אמריקאי",
          "08/02/18",
          760000,
          1.170303255,
          31.254586849332,
          0,
          44.69,
          0.01
        ],
        [
          "אופציה לס דולר שקל P345 04/18- חוזים סחירים ואופציות בישראל",
          29992816,
          "אחר",
          "דולר אמריקאי",
          "13/12/17",
          820000,
          0.15703786179044207,
          4.52501457991923,
          0,
          6.47,
          0.0
        ],
        [
          "Energy ev1  option- Energy Vision",
          29992820,
          "Utilities",
          "דולר אמריקאי",
          "20/12/17",
          66,
          1700.565,
          3.9440183706,
          0,
          5.64,
          0.0
        ]
      ]
    },
    "לא סחיר - חוזים עתידיים": {
      "columns": [
        "שם המנפיק/שם נייר ערך",
        "מספר ני\"ע",
        "ענף מסחר",
        "סוג מטבע",
        "תאריך רכישה",
        "ערך נקוב",
        "שער",
        "שווי הוגן",
        "שעור מנכסי אפיק ההשקעה",
        "שעור מסך נכסי השקעה"
      ],
      "data": [
        [
          "FWD CCY\\ILS 20180111 USD\\ILS 3.3586000 20190111- בנק לאומי לישראל בע\"מ",
          90005881,
          "ל.ר.",
          "דולר אמריקאי",
          "11/01/18",
          -1908700,
          9.322277054108241,
          -177.934302131764,
          13.29,
          -0.08
        ],
        [
          "FWD CCY\\ILS 20180123 DKK\\ILS 0.5644000 20180411- בנק לאומי לישראל בע\"מ",
          90005947,
          "ל.ר.",
          "כתר דני",
          "23/01/18",
          -151400,
          1.642413180882041,
          -2.48661355585541,
          0.19,
          0.0
        ],
        [
          "FWD CCY\\ILS 20180123 EUR\\ILS 4.1973000 20180411- בנק לאומי לישראל בע\"מ",
          90005945,
          "ל.ר.",
          "אירו",
          "23/01/18",
          -62400,
          13.211739130434792,
          -8.24412521739131,
          0.62,
          0.0
        ],
        [
          "FWD CCY\\ILS 20180123 EUR\\ILS 4.1998000 20180411- בנק לאומי לישראל בע\"מ",
          90005949,
          "ל.ר.",
          "אירו",
          "23/01/18",
          -941200,
          12.962071713147365,
          -121.999018964143,
          9.11,
          -0.05
        ],
        [
          "FWD CCY\\ILS 20180212 EUR\\ILS 4.3489000 20190213- בנק לאומי לישראל בע\"מ",
          90006095,
          "ל.ר.",
          "אירו",
          "12/02/18",
          -23200,
          0.5462396121883664,
          -0.126727590027701,
          0.01,
          0.0
        ],
        [
          "FWD CCY\\ILS 20180213 EUR\\ILS 4.3704000 20190213- בנק לאומי לישראל בע\"מ",
          90006114,
          "ל.ר.",
          "אירו",
          "13/02/18",
          -559800,
          -1.6019028871391103,
          8.96745236220474,
          -0.67,
          0.0
        ],
        [
          "FWD CCY\\ILS 20180312 EUR\\ILS 4.2450000 20180614- בנק לאומי לישראל בע\"מ",
          90006270,
          "ל.ר.",
          "אירו",
          "12/03/18",
          -169200,
          8.808222748815188,
          -14.9035128909953,
          1.11,
          -0.01
        ],
        [
          "004 20250831 ILS ILS TELBOR FLOAT FIXED 0 1.2915- בנק לאומי לישראל בע\"מ",
          90005068,
          "Other",
          "שקל חדש",
          "19/09/17",
          20000,
          -0.67614935064935,
          -0.13522987012987,
          0.01,
          0.0
        ],
        [
          "004 20250831 ILS ILS TELBOR FLOAT FIXED 0 1.53- בנק לאומי לישראל בע\"מ",
          90002818,
          "Other",
          "שקל חדש",
          "16/11/16",
          10108000,
          -2.6097032967033043,
          -263.78880923077,
          19.7,
          -0.12
        ],
        [
          "004 20250831 ILS ILS TELBOR FLOAT FIXED 0 1.715- בנק לאומי לישראל בע\"מ",
          90002823,
          "Other",
          "שקל חדש",
          "16/11/16",
          2260000,
          -4.04094191919192,
          -91.3252873737374,
          6.82,
          -0.04
        ],
        [
          "004 20250831 ILS ILS TELBOR FLOAT FIXED 0 1.87- בנק לאומי לישראל בע\"מ",
          90003581,
          "Other",
          "שקל חדש",
          "16/02/17",
          2176000,
          -5.2400625,
          -114.02376,
          8.52,
          -0.05
        ],
        [
          "004 20250831 ILS ILS TELBOR FLOAT FIXED 0 2.035- בנק לאומי לישראל בע\"מ",
          90003139,
          "Other",
          "שקל חדש",
          "15/12/16",
          3319000,
          -6.516598726114643,
          -216.285911719745,
          16.16,
          -0.1
        ],
        [
          "004 20250831 ILS ILS TELBOR FLOAT FIXED 0 1.457- חוזים סחירים ואופציות בישראל",
          90004616,
          "Other",
          "שקל חדש",
          "18/07/17",
          135000,
          -2.0449354838709706,
          -2.76066290322581,
          0.21,
          0.0
        ],
        [
          "004 20250831 ILS ILS TELBOR FLOAT FIXED 0 1.98- חוזים עתידיים בחול",
          90003110,
          "Other",
          "שקל חדש",
          "12/12/16",
          5479000,
          -6.09109090909091,
          -333.730870909091,
          24.93,
          -0.15
        ]
      ]
    },
    "לא סחיר - מוצרים מובנים": {
      "columns": [
        "שם המנפיק/שם נייר ערך",
        "מספר ני\"ע",
        "נכס הבסיס",
        "דירוג",
        "שם מדרג",
        "תאריך רכישה",
        "מח\"מ",
        "סוג מטבע",
        "שיעור ריבית",
        "תשואה לפידיון",
        "ערך נקוב",
        "שער",
        "שווי הוגן",
        "שעור מערך נקוב מונפק",
        "שעור מנכסי אפיק ההשקעה",
        "שעור מסך נכסי השקעה"
      ],
      "data": [
        [
          "מימון ישיר 1 לס- מימון ישיר הנפקות  בע\"מ",
          1133743,
          "אשראי",
          "AAA.IL",
          "S&P מעלות",
          "19/11/14",
          0.71,
          "שקל חדש",
          1.55,
          0.05,
          11746.16,
          101.13,
          11.878891608,
          0.01,
          0.97,
          0.01
        ],
        [
          "AESOP 2016-2X A- Avis Budget Rental Car Funding",
          "usu05376cg81",
          "אשראי",
          "AAA",
          "S&P",
          "26/05/16",
          4.15,
          "דולר אמריקאי",
          2.72,
          3.05,
          29000.0,
          98.06,
          99.9290236,
          0.01,
          8.15,
          0.04
        ],
        [
          "BAMLL 2015-200X A- Bank of America",
          "USU0602UAA08",
          "אשראי",
          "AAA",
          "S&P",
          "19/04/15",
          12.03,
          "דולר אמריקאי",
          3.22,
          2.83,
          248000.0,
          98.83,
          861.2757776,
          0.03,
          70.27,
          0.38
        ],
        [
          "Mad 2015-11/144A/D- Madison Avenue Trust",
          "US556227AJ56",
          "אשראי",
          "BBB-",
          "S&P",
          "21/09/15",
          6.59,
          "דולר אמריקאי",
          3.55,
          2.62,
          75000.0,
          95.82,
          252.53361,
          0.06,
          20.6,
          0.11
        ]
      ]
    },
    "הלוואות": {
      "columns": [
        "שם המנפיק/שם נייר ערך",
        "קונסורציום כן/לא",
        "מספר ני\"ע",
        "מספר מנפיק",
        "דירוג",
        "תאריך רכישה",
        "שם מדרג",
        "מח\"מ",
        "סוג מטבע",
        "שיעור ריבית ממוצע",
        "תשואה לפידיון",
        "ערך נקוב",
        "שער",
        "שווי הוגן",
        "שעור מנכסי אפיק ההשקעה",
        "שעור מסך נכסי השקעה",
        "מעלות",
        "שקל חדש"
      ],
      "data": [
        [
          "הלוואה 6 2012-2013",
          "כן",
          29992016,
          232,
          "AA.IL",
          "24/12/14",
          "S&P מעלות",
          2.75,
          "שקל חדש",
          6.0,
          2.93,
          893680.35,
          110.2,
          984.8357457,
          10.96,
          0.43,
          "",
          ""
        ],
        [
          "הלוואה 8 05/2013",
          "כן",
          "232-92321020",
          232,
          "AA.IL",
          "22/05/13",
          "S&P מעלות",
          0.98,
          "דולר אמריקאי",
          3.25,
          3.56,
          228745.92,
          103.27,
          830.097853306176,
          9.24,
          0.37,
          "",
          ""
        ],
        [
          "הלוואה 24 12/2015",
          "לא",
          1127091,
          1343,
          "Aa3.IL",
          "31/12/15",
          "מידרוג",
          1.15,
          "שקל חדש",
          2.64,
          0.65,
          57941.17,
          102.4,
          59.33175808,
          0.66,
          0.03,
          "",
          ""
        ],
        [
          "הלוואה 32 12/2016",
          "לא",
          29992732,
          1343,
          "Aa3.IL",
          "07/12/16",
          "מידרוג",
          2.16,
          "שקל חדש",
          2.55,
          1.1,
          140740.56,
          102.16,
          143.780556096,
          1.6,
          0.06,
          "",
          ""
        ],
        [
          "הלוואה 34.1 03/2017",
          "לא",
          29992756,
          390,
          "AA-.IL",
          "23/03/17",
          "S&P מעלות",
          1.82,
          "שקל חדש",
          0.25,
          0.27,
          892000.0,
          100.06027396860986,
          892.5376438,
          9.94,
          0.39,
          "",
          ""
        ],
        [
          "הלוואה 34.1 03/2017",
          "לא",
          29992757,
          390,
          "AA-.IL",
          "23/03/17",
          "S&P מעלות",
          2.58,
          "שקל חדש",
          0.0,
          0.0,
          -892000.0,
          100.0,
          -892.0,
          -9.93,
          -0.39,
          "",
          ""
        ],
        [
          "הלוואה 47 12/2014",
          "לא",
          1127090,
          1241,
          "Aa3.IL",
          "30/12/14",
          "מידרוג",
          0.85,
          "שקל חדש",
          2.33,
          0.4,
          57608.55,
          101.74,
          58.61093877,
          0.65,
          0.03,
          "",
          ""
        ],
        [
          "הלוואה 22 09/2015",
          "כן",
          99952483,
          12399,
          "A+.IL",
          "20/09/15",
          "S&P מעלות",
          4.57,
          "שקל חדש",
          2.75,
          2.36,
          269455.37,
          105.64,
          284.652652868,
          3.17,
          0.13,
          "",
          ""
        ],
        [
          "הלוואה 9 06/2013",
          "כן",
          29992039,
          12399,
          "A+.IL",
          "01/10/13",
          "S&P מעלות",
          4.21,
          "שקל חדש",
          5.15,
          0.86,
          921669.16,
          119.38,
          1100.288643208,
          12.25,
          0.48,
          "",
          ""
        ],
        [
          "הלוואה 14 04/2014",
          "לא",
          29993113,
          12751,
          "Baa1.IL",
          "28/04/14",
          "מידרוג",
          2.06,
          "שקל חדש",
          4.55,
          1.05,
          351094.9,
          110.61,
          388.34606889,
          4.32,
          0.17,
          "",
          ""
        ],
        [
          "הלוואה 15 07/2014",
          "לא",
          29992219,
          12786,
          "Baa3.IL",
          "30/07/14",
          "מידרוג",
          0.34,
          "שקל חדש",
          5.25,
          1.16,
          1365334.0,
          100.9,
          1377.622006,
          15.34,
          0.61,
          "",
          ""
        ],
        [
          "הלוואה 17 10/2014",
          "לא",
          29992247,
          10721,
          0,
          "20/10/14",
          "לא מדורג",
          1.45,
          "שקל חדש",
          5.0,
          1.81,
          146573.25,
          106.8,
          156.540231,
          1.74,
          0.07,
          "",
          ""
        ],
        [
          "הלוואה 19 05/2015",
          "כן",
          90146006,
          11248,
          0,
          "06/05/15",
          "לא מדורג",
          0.25,
          "שקל חדש",
          6.75,
          1.79,
          92504.68,
          102.92,
          95.205816656,
          1.06,
          0.04,
          "",
          ""
        ],
        [
          "הלוואה 25 02/2016",
          "לא",
          29992676,
          421,
          0,
          "15/02/16",
          "לא מדורג",
          0.5,
          "שקל חדש",
          6.5,
          8.25,
          84000.0,
          101.0,
          84.84,
          0.94,
          0.04,
          "",
          ""
        ],
        [
          "הלוואה 28 05/2016",
          "לא",
          299926970,
          12988,
          0,
          "31/12/17",
          "לא מדורג",
          2.14,
          "שקל חדש",
          0.0,
          0.0,
          470031.53,
          100.42754200000009,
          472.041112203993,
          5.26,
          0.21,
          "",
          ""
        ],
        [
          "הלוואה 29 05/2016",
          "לא",
          29992700,
          421,
          0,
          "30/05/16",
          "לא מדורג",
          0.5,
          "שקל חדש",
          4.9,
          4.58,
          67167.0,
          100.71,
          67.6438857,
          0.75,
          0.03,
          "",
          ""
        ],
        [
          "הלוואה 36 08/2017",
          "לא",
          29992786,
          13055,
          0,
          "03/08/17",
          "לא מדורג",
          3.91,
          "שקל חדש",
          5.0,
          4.04,
          137000.0,
          105.06,
          143.9322,
          1.6,
          0.06,
          "",
          ""
        ],
        [
          "הלוואה 27 03/2016",
          "לא",
          29992685,
          1420,
          "AA+.IL",
          "31/03/16",
          "S&P מעלות",
          0.01,
          "שקל חדש",
          1.35,
          0.91,
          736000.0,
          100.33,
          738.4288,
          8.22,
          0.33,
          "",
          ""
        ],
        [
          "הלוואה 7 02/2013",
          "לא",
          29991948,
          1173,
          "A+.IL",
          "01/10/13",
          "S&P מעלות",
          1.87,
          "שקל חדש",
          3.4,
          0.27,
          812000.0,
          106.68,
          866.2416,
          9.64,
          0.38,
          "",
          ""
        ],
        [
          "הלוואה 31 10/2016",
          "כן",
          29992726,
          611745192,
          "BBB",
          "28/10/16",
          "פנימי",
          2.49,
          "דולר אמריקאי",
          5.88,
          6.9,
          68675.47,
          100.32835602687986,
          242.118008737192,
          2.7,
          0.11,
          "",
          ""
        ],
        [
          "הלוואה 35.1 04/2017",
          "כן",
          29992772,
          194680,
          "BBB",
          "30/04/17",
          "S&P",
          1.0,
          "לירה שטרלינג",
          1.0,
          1.15,
          46305.62,
          100.01944450803164,
          228.98876348638,
          2.55,
          0.1,
          "",
          ""
        ],
        [
          "הלוואה 35 04/2017",
          "כן",
          29992774,
          194680,
          "BBB",
          "20/09/17",
          "S&P",
          1.01,
          "לירה שטרלינג",
          5.0,
          5.91,
          36694.38,
          101.6429868194039,
          184.405131812771,
          2.05,
          0.08,
          "",
          ""
        ],
        [
          "הלוואה 35.2 04/2017",
          "כן",
          29992773,
          194680,
          "BBB",
          "30/04/17",
          "S&P",
          1.75,
          "לירה שטרלינג",
          0.0,
          0.0,
          -46305.62,
          100.0,
          -228.944246404,
          -2.55,
          -0.1,
          "",
          ""
        ],
        [
          "הלוואה 33 02/2017",
          "כן",
          29992749,
          67011330,
          "B",
          "23/02/17",
          "S&P",
          4.99,
          "אירו",
          5.25,
          3.78,
          67000.0,
          100.63778427327797,
          291.879363176651,
          3.25,
          0.13,
          "",
          ""
        ],
        [
          "הלוואה 37 08/2017",
          "כן",
          29992787,
          814070775,
          0,
          "03/08/17",
          "לא מדורג",
          2.16,
          "דולר אמריקאי",
          5.88,
          3.37,
          33508.32,
          100.30000953703285,
          118.101492419128,
          1.31,
          0.05,
          "",
          ""
        ],
        [
          "הלוואה 3 08/2010",
          "לא",
          29991603,
          152554,
          0,
          "01/10/13",
          "לא מדורג",
          1.6,
          "אירו",
          17.0,
          88.59,
          19600.0,
          37.574,
          31.8794649152,
          0.35,
          0.01,
          "",
          ""
        ],
        [
          "הלוואה 5 03/2011",
          "לא",
          29991660,
          16302,
          0,
          "01/10/13",
          "לא מדורג",
          4.78,
          "אירו",
          7.0,
          7.08,
          59940.64,
          100.36369999999992,
          260.414738613325,
          2.9,
          0.11,
          "",
          ""
        ]
      ]
    },
    "פקדונות מעל 3 חודשים": {
      "columns": [
        "שם המנפיק/שם נייר ערך",
        "מספר ני\"ע",
        "מספר מנפיק",
        "דירוג",
        "שם מדרג",
        "מח\"מ",
        "סוג מטבע",
        "תנאי ושיעור ריבית",
        "תשואה לפידיון",
        "ערך נקוב",
        "שער",
        "שווי הוגן",
        "שעור מנכסי אפיק ההשקעה",
        "שעור מסך נכסי השקעה"
      ],
      "data": [
        [
          "הלוואה 28 05/2016 פקדון",
          299926971,
          10,
          "AA.IL",
          "S&P מעלות",
          "",
          "שקל חדש",
          0,
          0.0,
          23820.68,
          88.440381,
          21.0671001487908,
          0.72,
          0.01
        ],
        [
          "ביטחונות CSA במטבע 20001 (OTC)- בנק לאומי לישראל בע\"מ",
          77720001,
          10,
          "AAA.IL",
          "S&P מעלות",
          0.01,
          "דולר אמריקאי",
          0,
          0.01,
          340000.0,
          100.0,
          1194.76,
          40.63,
          0.53
        ],
        [
          "ביטחונות חוזים עתידיים במטבע 20001",
          88820001,
          10,
          "AAA.IL",
          "S&P מעלות",
          0.01,
          "דולר אמריקאי",
          0,
          0.01,
          490896.56,
          100.0,
          1725.01051184,
          58.66,
          0.76
        ]
      ]
    },
    "זכויות מקרקעין": {
      "columns": [
        "שם המנפיק/שם נייר ערך",
        "תאריך שערוך אחרון",
        "אופי הנכס",
        "שעור תשואה במהלך התקופה",
        "סוג מטבע",
        "שווי משוערך",
        "שעור מנכסי אפיק ההשקעה",
        "שעור מסך נכסי השקעה",
        "כתובת הנכס"
      ],
      "data": [
        [
          "נדל\"ן בזק חיפה- נדלן בזק חיפה",
          "04/05/17",
          "משרדים",
          1.52,
          "שקל חדש",
          381.61064833,
          27.47,
          0.17,
          "דרך בר יהודה 31 מפרץ חיפה"
        ],
        [
          "Dortmund- Lander Sarl",
          "31/12/17",
          "משרדים",
          2.2,
          "אירו",
          158.028168666413,
          11.37,
          0.07,
          "Kammerstuck 15, 44357 Dortmund"
        ],
        [
          "Ludwigshafen Real Estate- Ludwigshafen Real Estate",
          "13/12/17",
          "משרדים",
          1.92,
          "אירו",
          849.792216711484,
          61.16,
          0.37,
          "Rheinallee 11, 67061 Ludwigshafen am Rhein"
        ]
      ]
    },
    "השקעות אחרות ": {
      "columns": [
        "שם המנפיק/שם נייר ערך",
        "מספר ני\"ע",
        "דירוג",
        "שם המדרג",
        "שעור הריבית",
        "סוג מטבע",
        "תשואה לפדיון",
        "שווי הוגן",
        "שעור מנכסי אפיק ההשקעה",
        "שעור מסך נכסי השקעה"
      ],
      "data": [
        [
          "זכאים",
          28080000,
          0,
          "לא מדורג",
          0,
          "שקל חדש",
          0,
          -7.04473,
          27.06,
          0.0
        ],
        [
          "זכאים מס עמיתים",
          28200000,
          0,
          "לא מדורג",
          0,
          "שקל חדש",
          0,
          -32.94274,
          126.54,
          -0.01
        ],
        [
          "חייבים",
          27960000,
          0,
          "לא מדורג",
          0,
          "שקל חדש",
          0,
          13.95423,
          -53.6,
          0.01
        ]
      ]
    },
    "יתרת התחייבות להשקעה": {
      "columns": [
        "שם המנפיק/שם נייר ערך",
        "סכום ההתחייבות",
        "תאריך סיום ההתחייבות"
      ],
      "data": [
        [
          "אביב 2",
          0.0,
          43040
        ],
        [
          "אוריגו",
          0.0,
          43245
        ],
        [
          "גלילות 1",
          0.0,
          43313
        ],
        [
          "גלילות 2",
          0.0,
          44713
        ],
        [
          "גלילות - שותפות 1",
          17.18346,
          "עד למועד פירוק שותפות"
        ],
        [
          "יסודות",
          172.073,
          44166
        ],
        [
          "Klirmark 1",
          0.0,
          43160
        ],
        [
          "Klirmark 2",
          548.876,
          44835
        ],
        [
          "לול",
          0.0,
          43770
        ],
        [
          "מאגמה",
          113.85359999999999,
          45536
        ],
        [
          "מוסטנג",
          0.0,
          43344
        ],
        [
          "נווה אילן",
          17.834,
          "עד למועד פירוק שותפות"
        ],
        [
          "נוי 1 תשתיות ואנרגיה",
          28.744338133333308,
          44409
        ],
        [
          "נוי 2 תשתיות ואנרגיה",
          853.0149382787,
          "עד למועד פירוק שותפות"
        ],
        [
          "סקי",
          0.0,
          42948
        ],
        [
          "פונטיפקס II",
          0.0,
          42887
        ],
        [
          "פונטיפקס III",
          0.0,
          44470
        ],
        [
          "פונטיפקס 4",
          30.923199999999998,
          44105
        ],
        [
          "פימי 2",
          0.0,
          42644
        ],
        [
          "פימי 5",
          0.0,
          44774
        ],
        [
          "ריאלטי 1",
          0.0,
          43282
        ],
        [
          "ריאלטי 2",
          69.32477162886599,
          44593
        ],
        [
          "ריאלטי 3",
          344.524,
          44713
        ],
        [
          "STATE OF MIND VENTURES",
          23.272856544000003,
          44440
        ],
        [
          "תשתיות לישראל 2",
          23.452436,
          44409
        ],
        [
          "ISF",
          0.0,
          45627
        ],
        [
          "KCPS",
          0.0,
          43221
        ],
        [
          "KEDMA 2",
          0.0,
          45748
        ],
        [
          "Vintage",
          52.68984931839999,
          43344
        ],
        [
          "קוגיטו קפיטל (קרן להלוואות לעסקים קטנים)",
          83.77242761111111,
          43891
        ],
        [
          "הלוואה 28 05/2016 - קרן למתן הלוואות לעסקים קטנים בערבות מדינה",
          1724.8869306870986,
          46143
        ],
        [
          "הלוואה 34 03/2017 אלוני חץ",
          892.0,
          "25/01/2020"
        ],
        [
          "נוי נגב אנרגיה",
          130.652,
          "עד למועד פירוק השותפות"
        ],
        [
          "פנינסולה",
          72.82206827926159,
          44256
        ],
        [
          "GATEWOOD",
          63.4168066,
          46174
        ],
        [
          "יסודות אנקס",
          240.64,
          44166
        ],
        [
          "FORMA",
          972.3687914587069,
          46631
        ],
        [
          "קרן קוגיטו משלימה",
          0.0,
          47119
        ],
        [
          "נוי כוכב הירדן",
          78.643,
          "עד למועד פירוק השותפות"
        ],
        [
          "וי 1 תשתיות ואנרגיה פשה",
          0.0,
          44409
        ],
        [
          "נוי 2 תשתיות ואנרגיה פשה",
          0.0,
          44409
        ],
        [
          "יסודות2",
          444.08456413999994,
          45292
        ],
        [
          "ARES 4",
          287.753571715101,
          44795
        ],
        [
          "Alto 2",
          0.0,
          42979
        ],
        [
          "AVENUE 3",
          93.37536456971252,
          44317
        ],
        [
          "בראק",
          0.0,
          43544
        ],
        [
          "נוי פסולת לאנרגיה - שותפות 1",
          18.099938673789527,
          "עד למועד פירוק שותפות"
        ],
        [
          "נוי פסולת לאנרגיה - שותפות 2",
          6.228701182320011,
          "עד למועד פירוק שותפות"
        ],
        [
          "דנמרק IPDS P S",
          133.1332681998,
          43435
        ],
        [
          "ICG ASIA PASIFIC",
          88.7942810964574,
          45444
        ],
        [
          "ICG NORTH AMERICA",
          205.5179159655314,
          45413
        ],
        [
          "Kreos Capital",
          69.83228,
          45931
        ],
        [
          "NETZ",
          0.0,
          43709
        ],
        [
          "Qumra",
          17.380243999999998,
          44562
        ],
        [
          "STAGE ONE 2",
          15.039990201231962,
          44562
        ],
        [
          "ANACAP",
          141.14884174277333,
          45047
        ],
        [
          "הלוואה 35 10/2016 -  Hudson Yards",
          229.55005495963195,
          43800
        ],
        [
          "הלוואה 35 04/2017 -  מלון הית'רו לונדון",
          228.94426167093235,
          43554
        ],
        [
          "הלוואה ל- Long Island City הלוואה 37 08/2017",
          172.52018689941002,
          44012
        ],
        [
          "פרספטיב",
          70.2046247,
          "עד למועד פירוק שותפות"
        ],
        [
          "MIDEAL",
          402.10582400000004,
          46357
        ],
        [
          "CRESCENT",
          147.18389,
          44531
        ],
        [
          "ICG SECONDARIES FUND",
          189.82628,
          45807
        ],
        [
          "SIGNAL",
          83.5884028097674,
          45901
        ],
        [
          "INVESTCORP",
          94.04662685246306,
          45169
        ],
        [
          "STAGE ONE 3",
          12.7636366,
          46621
        ]
      ]
    }
  }
}