{
  "info": {
    "key": "g8630_0118"
  },
  "sheets": {
    "מזומנים": {
      "columns": [
        "שם נ\"ע",
        "מספר ני\"ע",
        "מספר מנפיק",
        "דירוג",
        "שם מדרג",
        "סוג מטבע",
        "שיעור ריבית",
        "תשואה לפידיון",
        "שווי שוק",
        "שיעור מנכסי אפיק ה השקעה",
        "שעור מנכסי השקעה"
      ],
      "data": [
        [
          "מזומן (מזרחי)",
          4,
          20,
          "AAA IL",
          "S&P מעלות",
          "שקל חדש",
          "",
          "",
          0.07,
          0.0,
          0.0
        ],
        [
          "מזומן מחוץ למזרחי (מזרחי)",
          419259239,
          20,
          "AAA IL",
          "S&P מעלות",
          "שקל חדש",
          "",
          "",
          0.2,
          0.0,
          0.0
        ],
        [
          "שקל חדש עתידי (מזרחי)",
          5000,
          20,
          "AAA IL",
          "S&P מעלות",
          "שקל חדש",
          "",
          "",
          -522.21,
          -0.0261,
          -0.0027
        ],
        [
          "דולר אמריקאי (מזרחי)",
          14,
          20,
          "AAA IL",
          "S&P מעלות",
          "דולר אמריקאי",
          "",
          "",
          10.52,
          0.0005,
          0.0001
        ],
        [
          "יין עתידי (מזרחי)",
          5002,
          20,
          "AAA IL",
          "S&P מעלות",
          "יין יפני",
          "",
          "",
          215.6,
          0.0108,
          0.0011
        ],
        [
          "מזומן אירו (מזרחי)",
          1010,
          20,
          "AAA IL",
          "S&P מעלות",
          "אירו",
          "",
          "",
          735.53,
          0.0367,
          0.0038
        ],
        [
          "מזומן דולר הונג קונג (מזרחי)",
          1032,
          20,
          "AAA IL",
          "S&P מעלות",
          "דולר הונג קונג",
          "",
          "",
          0.0,
          0.0,
          0.0
        ],
        [
          "מזומן יין יפני (מזרחי)",
          1002,
          20,
          "AAA IL",
          "S&P מעלות",
          "יין יפני",
          "",
          "",
          21.62,
          0.0011,
          0.0001
        ],
        [
          "מזומן לירה שטרלינג (מזרחי)",
          1004,
          20,
          "AAA IL",
          "S&P מעלות",
          "לירה שטרלינג",
          "",
          "",
          14.18,
          0.0007,
          0.0001
        ],
        [
          "מעבר דולר תקבול תשלם (מזרחי)",
          419259007,
          20,
          "AAA IL",
          "S&P מעלות",
          "דולר אמריקאי",
          "",
          "",
          0.01,
          0.0,
          0.0
        ],
        [
          "פח\"ק 1802 (מזרחי)",
          100118020,
          20,
          "AAA IL",
          "S&P מעלות",
          "שקל חדש",
          "",
          "",
          17861.14,
          0.892,
          0.0921
        ],
        [
          "HSBC USD (HSBC)",
          "HSBC USD",
          "",
          "AA-",
          "Fitch",
          "דולר אמריקאי",
          "",
          "",
          1687.55,
          0.0843,
          0.0087
        ]
      ]
    },
    "מניות": {
      "columns": [
        "שם נ\"ע",
        "מספר ני\"ע",
        "זירת מסחר",
        "ספק מידע",
        "מספר מנפיק",
        "ענף מסחר",
        "סוג מטבע",
        "ערך נקוב",
        "שער",
        "פידיון/ריבית לקבל",
        "שווי שוק",
        "שעור מערך נקוב מונפק",
        "שיעור מנכסי אפיק ההשקעה",
        "שעור מנכסי השקעה"
      ],
      "data": [
        [
          "בינלאומי 5",
          593038,
          "TASE",
          "",
          520029083,
          "בנקים",
          "שקל חדש",
          15267.0,
          7390.0,
          0.0,
          1128.23,
          0.0002,
          0.0134,
          0.0058
        ],
        [
          "דיסקונט",
          691212,
          "TASE",
          "",
          520007030,
          "בנקים",
          "שקל חדש",
          295219.0,
          1006.0,
          0.0,
          2969.9,
          0.0003,
          0.0354,
          0.0153
        ],
        [
          "לאומי",
          604611,
          "TASE",
          "",
          520018078,
          "בנקים",
          "שקל חדש",
          202413.0,
          2111.0,
          0.0,
          4272.94,
          0.0001,
          0.0509,
          0.022
        ],
        [
          "מזרחי",
          695437,
          "TASE",
          "",
          520000522,
          "בנקים",
          "שקל חדש",
          35426.0,
          6703.0,
          0.0,
          2374.6,
          0.0002,
          0.0283,
          0.0122
        ],
        [
          "פועלים",
          662577,
          "TASE",
          "",
          520000118,
          "בנקים",
          "שקל חדש",
          173079.0,
          2404.0,
          0.0,
          4160.82,
          0.0001,
          0.0496,
          0.0215
        ],
        [
          "הפניקס 1 (*) (*)",
          767012,
          "TASE",
          "",
          520017450,
          "ביטוח",
          "שקל חדש",
          29220.0,
          1926.0,
          0.0,
          562.78,
          0.0001,
          0.0067,
          0.0029
        ],
        [
          "הראל",
          585018,
          "TASE",
          "",
          520033986,
          "ביטוח",
          "שקל חדש",
          32622.0,
          2773.0,
          0.0,
          904.61,
          0.0001,
          0.0108,
          0.0047
        ],
        [
          "שופרסל",
          777037,
          "TASE",
          "",
          520022732,
          "מסחר",
          "שקל חדש",
          35944.0,
          2233.0,
          0.0,
          802.63,
          0.0001,
          0.0096,
          0.0041
        ],
        [
          "אירפורט סיטי",
          1095835,
          "TASE",
          "",
          511659401,
          "נדל\"ן ובינוי",
          "שקל חדש",
          20008.46,
          3778.0,
          0.0,
          755.92,
          0.0002,
          0.009,
          0.0039
        ],
        [
          "אלוני חץ",
          390013,
          "TASE",
          "",
          520038506,
          "נדל\"ן ובינוי",
          "שקל חדש",
          34611.0,
          3161.0,
          22.5,
          1116.55,
          0.0002,
          0.0133,
          0.0058
        ],
        [
          "אמות",
          1097278,
          "TASE",
          "",
          520026683,
          "נדל\"ן ובינוי",
          "שקל חדש",
          37136.0,
          1878.0,
          0.0,
          697.41,
          0.0001,
          0.0083,
          0.0036
        ],
        [
          "גזית גלוב",
          126011,
          "TASE",
          "",
          520033234,
          "נדל\"ן ובינוי",
          "שקל חדש",
          29439.0,
          3463.0,
          0.0,
          1019.47,
          0.0002,
          0.0122,
          0.0053
        ],
        [
          "מליסרון",
          323014,
          "TASE",
          "",
          520037789,
          "נדל\"ן ובינוי",
          "שקל חדש",
          5074.0,
          13970.0,
          0.0,
          708.84,
          0.0001,
          0.0084,
          0.0037
        ],
        [
          "עזריאלי",
          1119478,
          "TASE",
          "",
          510960719,
          "נדל\"ן ובינוי",
          "שקל חדש",
          10765.0,
          16810.0,
          0.0,
          1809.6,
          0.0001,
          0.0216,
          0.0093
        ],
        [
          "סודהסטרים",
          1121300,
          "TASE",
          "",
          513951251,
          "מזון",
          "שקל חדש",
          5515.0,
          31810.0,
          0.0,
          1754.32,
          0.0003,
          0.0209,
          0.009
        ],
        [
          "פרוטרום",
          1081082,
          "TASE",
          "",
          520042805,
          "מזון",
          "שקל חדש",
          12081.0,
          32110.0,
          0.0,
          3879.21,
          0.0002,
          0.0462,
          0.02
        ],
        [
          "שטראוס עלית",
          746016,
          "TASE",
          "",
          520003781,
          "מזון",
          "שקל חדש",
          13093.0,
          7550.0,
          0.0,
          988.52,
          0.0001,
          0.0118,
          0.0051
        ],
        [
          "כיל",
          281014,
          "TASE",
          "",
          520027830,
          "כימיה גומי ופלסטיק",
          "שקל חדש",
          145900.0,
          1480.0,
          0.0,
          2159.32,
          0.0001,
          0.0257,
          0.0111
        ],
        [
          "חברה לישראל",
          576017,
          "TASE",
          "",
          520028010,
          "השקעה ואחזקות",
          "שקל חדש",
          1171.0,
          65880.0,
          0.0,
          771.45,
          0.0002,
          0.0092,
          0.004
        ],
        [
          "קבוצת דלק (*) (*)",
          1084128,
          "TASE",
          "",
          520044322,
          "השקעה ואחזקות",
          "שקל חדש",
          1063.0,
          59230.0,
          0.0,
          629.61,
          0.0001,
          0.0075,
          0.0032
        ],
        [
          "דלק קדוחים (*) (*)",
          475020,
          "TASE",
          "",
          550013098,
          "חיפושי נפט וגז",
          "שקל חדש",
          133966.0,
          1077.0,
          0.0,
          1442.81,
          0.0001,
          0.0172,
          0.0074
        ],
        [
          "ישראמקו",
          232017,
          "TASE",
          "",
          550010003,
          "חיפושי נפט וגז",
          "שקל חדש",
          2627977.0,
          40.9,
          0.0,
          1074.84,
          0.0002,
          0.0128,
          0.0055
        ],
        [
          "בזק",
          230011,
          "TASE",
          "",
          520031931,
          "תקשורת ומדיה",
          "שקל חדש",
          561108.0,
          448.0,
          0.0,
          2513.76,
          0.0002,
          0.03,
          0.013
        ],
        [
          "סלקום",
          1101534,
          "TASE",
          "",
          511930125,
          "תקשורת ומדיה",
          "שקל חדש",
          15376.0,
          2478.0,
          0.0,
          381.02,
          0.0002,
          0.0045,
          0.002
        ],
        [
          "פרטנר",
          1083484,
          "TASE",
          "",
          520044314,
          "תקשורת ומדיה",
          "שקל חדש",
          34453.0,
          1580.0,
          0.0,
          544.36,
          0.0002,
          0.0065,
          0.0028
        ],
        [
          "בזן",
          2590248,
          "TASE",
          "",
          520036658,
          "אנרגיה",
          "שקל חדש",
          486812.0,
          162.2,
          0.0,
          789.61,
          0.0002,
          0.0094,
          0.0041
        ],
        [
          "פז נפט",
          1100007,
          "TASE",
          "",
          510216054,
          "אנרגיה",
          "שקל חדש",
          2576.0,
          51550.0,
          101.44,
          1429.36,
          0.0002,
          0.017,
          0.0074
        ],
        [
          "נייס",
          273011,
          "TASE",
          "",
          520036872,
          "תוכנה ואינטרנט",
          "שקל חדש",
          14261.0,
          32570.0,
          0.0,
          4644.81,
          0.0002,
          0.0554,
          0.024
        ],
        [
          "טאואר",
          1082379,
          "TASE",
          "",
          520041997,
          "מוליכים למחצה",
          "שקל חדש",
          24970.0,
          9450.0,
          0.0,
          2359.66,
          0.0003,
          0.0281,
          0.0122
        ],
        [
          "מזור טכנו",
          1106855,
          "TASE",
          "",
          513009043,
          "מכשור רפואי",
          "שקל חדש",
          13260.0,
          10300.0,
          0.0,
          1365.78,
          0.0003,
          0.0163,
          0.007
        ],
        [
          "אופקו",
          1129543,
          "TASE",
          "",
          2279206,
          "השקעות במדעי החיים",
          "שקל חדש",
          84916.0,
          1100.0,
          0.0,
          934.08,
          0.0002,
          0.0111,
          0.0048
        ],
        [
          "אלביט מערכות",
          1081124,
          "TASE",
          "",
          520043027,
          "ביטחוניות",
          "שקל חדש",
          6505.0,
          42100.0,
          0.0,
          2738.61,
          0.0001,
          0.0326,
          0.0141
        ],
        [
          "אורמת טכנו",
          1134402,
          "TASE",
          "",
          511597239,
          "קלינטק",
          "שקל חדש",
          10267.64,
          20040.0,
          8.26,
          2065.9,
          0.0002,
          0.0246,
          0.0107
        ],
        [
          "טבע",
          629014,
          "TASE",
          "",
          520013954,
          "פארמה",
          "שקל חדש",
          64349.0,
          5956.0,
          0.0,
          3832.63,
          0.0001,
          0.0457,
          0.0198
        ],
        [
          "פריגו",
          1130699,
          "TASE",
          "",
          520037599,
          "פארמה",
          "שקל חדש",
          14144.0,
          28980.0,
          0.0,
          4098.93,
          0.0001,
          0.0489,
          0.0211
        ],
        [
          "אוצר השלטון",
          711010,
          "TASE",
          "",
          520019753,
          "בנקים",
          "שקל חדש",
          78.0,
          68150.0,
          0.0,
          53.16,
          0.0001,
          0.0006,
          0.0003
        ],
        [
          "פיבי",
          763011,
          "TASE",
          "",
          520029026,
          "בנקים",
          "שקל חדש",
          3147.0,
          8887.0,
          3.99,
          283.67,
          0.0001,
          0.0034,
          0.0015
        ],
        [
          "איידיאיי ביטוח",
          1129501,
          "TASE",
          "",
          513910703,
          "ביטוח",
          "שקל חדש",
          2233.0,
          22900.0,
          18.26,
          529.62,
          0.0002,
          0.0063,
          0.0027
        ],
        [
          "כלל עסקי ביטוח",
          224014,
          "TASE",
          "",
          520036120,
          "ביטוח",
          "שקל חדש",
          6343.0,
          6317.0,
          0.0,
          400.69,
          0.0001,
          0.0048,
          0.0021
        ],
        [
          "מגדל ביטוח",
          1081165,
          "TASE",
          "",
          520029984,
          "ביטוח",
          "שקל חדש",
          93552.0,
          374.3,
          0.0,
          350.17,
          0.0001,
          0.0042,
          0.0018
        ],
        [
          "מנורה",
          566018,
          "TASE",
          "",
          520007469,
          "ביטוח",
          "שקל חדש",
          7221.0,
          4492.0,
          0.0,
          324.37,
          0.0001,
          0.0039,
          0.0017
        ],
        [
          "אלקטרה צריכה",
          5010129,
          "TASE",
          "",
          520039967,
          "מסחר",
          "שקל חדש",
          2514.0,
          5396.0,
          0.0,
          135.66,
          0.0001,
          0.0016,
          0.0007
        ],
        [
          "דלק רכב (*) (*)",
          829010,
          "TASE",
          "",
          520033291,
          "מסחר",
          "שקל חדש",
          10636.0,
          2628.0,
          0.0,
          279.51,
          0.0001,
          0.0033,
          0.0014
        ],
        [
          "סקופ",
          288019,
          "TASE",
          "",
          520037425,
          "מסחר",
          "שקל חדש",
          1657.0,
          9753.0,
          0.0,
          161.61,
          0.0002,
          0.0019,
          0.0008
        ],
        [
          "קריסטל",
          258012,
          "TASE",
          "",
          520036732,
          "מסחר",
          "שקל חדש",
          754.0,
          10250.0,
          0.0,
          77.28,
          0.0001,
          0.0009,
          0.0004
        ],
        [
          "קרסו מר",
          1123850,
          "TASE",
          "",
          514065283,
          "מסחר",
          "שקל חדש",
          7096.0,
          2459.0,
          0.0,
          174.49,
          0.0001,
          0.0021,
          0.0009
        ],
        [
          "רמי לוי",
          1104249,
          "TASE",
          "",
          513770669,
          "מסחר",
          "שקל חדש",
          2051.0,
          17620.0,
          0.0,
          361.39,
          0.0002,
          0.0043,
          0.0019
        ],
        [
          "אל על",
          1087824,
          "TASE",
          "",
          520017146,
          "שרותים",
          "שקל חדש",
          75434.0,
          116.9,
          0.0,
          88.18,
          0.0002,
          0.0011,
          0.0005
        ],
        [
          "דנאל כא",
          314013,
          "TASE",
          "",
          520037565,
          "שרותים",
          "שקל חדש",
          1231.0,
          17580.0,
          3.08,
          219.49,
          0.0002,
          0.0026,
          0.0011
        ],
        [
          "איסתא",
          1081074,
          "TASE",
          "",
          520042763,
          "מלונאות ותיירות",
          "שקל חדש",
          1498.0,
          7622.0,
          0.0,
          114.18,
          0.0001,
          0.0014,
          0.0006
        ],
        [
          "אדגר",
          1820083,
          "TASE",
          "",
          520035171,
          "נדל\"ן ובינוי",
          "שקל חדש",
          15036.0,
          617.1,
          0.0,
          92.79,
          0.0001,
          0.0011,
          0.0005
        ],
        [
          "אזורים",
          715011,
          "TASE",
          "",
          520025990,
          "נדל\"ן ובינוי",
          "שקל חדש",
          24051.0,
          367.6,
          0.0,
          88.41,
          0.0001,
          0.0011,
          0.0005
        ],
        [
          "אלרוב נדלן ומלונאות",
          387019,
          "TASE",
          "",
          520038894,
          "נדל\"ן ובינוי",
          "שקל חדש",
          2146.0,
          12120.0,
          0.0,
          260.1,
          0.0001,
          0.0031,
          0.0013
        ],
        [
          "אפריקה נכסים",
          1091354,
          "TASE",
          "",
          510560188,
          "נדל\"ן ובינוי",
          "שקל חדש",
          3252.0,
          8640.0,
          0.0,
          280.97,
          0.0001,
          0.0033,
          0.0014
        ],
        [
          "אשטרום נכסים",
          251017,
          "TASE",
          "",
          520036617,
          "נדל\"ן ובינוי",
          "שקל חדש",
          9898.0,
          1692.0,
          5.71,
          173.18,
          0.0001,
          0.0021,
          0.0009
        ],
        [
          "אשטרום קבוצה מניה",
          1132315,
          "TASE",
          "",
          510381601,
          "נדל\"ן ובינוי",
          "שקל חדש",
          4189.0,
          1468.0,
          0.0,
          61.49,
          0.0001,
          0.0007,
          0.0003
        ],
        [
          "ביג",
          1097260,
          "TASE",
          "",
          513623314,
          "נדל\"ן ובינוי",
          "שקל חדש",
          1211.0,
          23430.0,
          0.0,
          283.74,
          0.0001,
          0.0034,
          0.0015
        ],
        [
          "בראק אן וי",
          1121607,
          "TASE",
          "",
          513890368,
          "נדל\"ן ובינוי",
          "שקל חדש",
          1176.0,
          41990.0,
          0.0,
          493.8,
          0.0002,
          0.0059,
          0.0025
        ],
        [
          "גב ים 1",
          759019,
          "TASE",
          "",
          520001736,
          "נדל\"ן ובינוי",
          "שקל חדש",
          325.0,
          165900.0,
          0.0,
          539.17,
          0.0002,
          0.0064,
          0.0028
        ],
        [
          "דמרי",
          1090315,
          "TASE",
          "",
          511399388,
          "נדל\"ן ובינוי",
          "שקל חדש",
          1592.0,
          6183.0,
          0.0,
          98.43,
          0.0001,
          0.0012,
          0.0005
        ],
        [
          "הכשרה הישוב",
          612010,
          "TASE",
          "",
          520020116,
          "נדל\"ן ובינוי",
          "שקל חדש",
          2503.0,
          3469.0,
          0.0,
          86.83,
          0.0001,
          0.001,
          0.0004
        ],
        [
          "ישראל קנדה",
          434019,
          "TASE",
          "",
          520039298,
          "נדל\"ן ובינוי",
          "שקל חדש",
          27507.0,
          391.3,
          2.85,
          110.49,
          0.0001,
          0.0013,
          0.0006
        ],
        [
          "ישרס",
          613034,
          "TASE",
          "",
          520017807,
          "נדל\"ן ובינוי",
          "שקל חדש",
          479.0,
          41480.0,
          1.92,
          200.61,
          0.0001,
          0.0024,
          0.001
        ],
        [
          "כלכלית",
          198010,
          "TASE",
          "",
          520017070,
          "נדל\"ן ובינוי",
          "שקל חדש",
          53100.0,
          848.2,
          0.0,
          450.39,
          0.0002,
          0.0054,
          0.0023
        ],
        [
          "לוינשטין נכסים",
          1119080,
          "TASE",
          "",
          511134298,
          "נדל\"ן ובינוי",
          "שקל חדש",
          1278.0,
          7312.0,
          0.0,
          93.45,
          0.0001,
          0.0011,
          0.0005
        ],
        [
          "מבני תעשיה",
          226019,
          "TASE",
          "",
          520024126,
          "נדל\"ן ובינוי",
          "שקל חדש",
          39689.0,
          488.2,
          0.0,
          193.76,
          0.0001,
          0.0023,
          0.001
        ],
        [
          "מגדלי הים התיכון",
          1131523,
          "TASE",
          "",
          512719485,
          "נדל\"ן ובינוי",
          "שקל חדש",
          21765.0,
          710.7,
          0.0,
          154.68,
          0.0002,
          0.0018,
          0.0008
        ],
        [
          "מגה אור",
          1104488,
          "TASE",
          "",
          513257873,
          "נדל\"ן ובינוי",
          "שקל חדש",
          4349.0,
          4467.0,
          2.28,
          196.55,
          0.0001,
          0.0023,
          0.001
        ],
        [
          "נורסטאר החזקות",
          723007,
          "TASE",
          "",
          4452879837,
          "נדל\"ן ובינוי",
          "שקל חדש",
          2972.0,
          6373.0,
          0.0,
          189.41,
          0.0001,
          0.0023,
          0.001
        ],
        [
          "נכסים בנין",
          699017,
          "TASE",
          "",
          520025438,
          "נדל\"ן ובינוי",
          "שקל חדש",
          718.0,
          29920.0,
          0.0,
          214.83,
          0.0001,
          0.0026,
          0.0011
        ],
        [
          "סאמיט",
          1081686,
          "TASE",
          "",
          520043720,
          "נדל\"ן ובינוי",
          "שקל חדש",
          10137.0,
          3074.0,
          0.0,
          311.61,
          0.0002,
          0.0037,
          0.0016
        ],
        [
          "סלע קפיטל",
          1109644,
          "TASE",
          "",
          513992529,
          "נדל\"ן ובינוי",
          "שקל חדש",
          43080.0,
          681.5,
          0.0,
          293.59,
          0.0003,
          0.0035,
          0.0015
        ],
        [
          "רבוע נדלן",
          1098565,
          "TASE",
          "",
          513765859,
          "נדל\"ן ובינוי",
          "שקל חדש",
          1321.0,
          13140.0,
          0.0,
          173.58,
          0.0001,
          0.0021,
          0.0009
        ],
        [
          "ריט1 (*) (*)",
          1098920,
          "TASE",
          "",
          513821488,
          "נדל\"ן ובינוי",
          "שקל חדש",
          43687.0,
          1439.0,
          0.0,
          628.66,
          0.0003,
          0.0075,
          0.0032
        ],
        [
          "שיכון ובינוי",
          1081942,
          "TASE",
          "",
          520036104,
          "נדל\"ן ובינוי",
          "שקל חדש",
          61662.0,
          577.5,
          0.0,
          356.1,
          0.0002,
          0.0042,
          0.0018
        ],
        [
          "נטו",
          168013,
          "TASE",
          "",
          520034109,
          "מזון",
          "שקל חדש",
          422.0,
          32620.0,
          0.0,
          137.66,
          0.0001,
          0.0016,
          0.0007
        ],
        [
          "קרור 1",
          621011,
          "TASE",
          "",
          520001546,
          "מזון",
          "שקל חדש",
          1435.0,
          10320.0,
          0.0,
          148.09,
          0.0001,
          0.0018,
          0.0008
        ],
        [
          "דלתא גליל",
          627034,
          "TASE",
          "",
          520025602,
          "אופנה והלבשה",
          "שקל חדש",
          2902.0,
          10320.0,
          0.0,
          299.49,
          0.0001,
          0.0036,
          0.0015
        ],
        [
          "פוקס",
          1087022,
          "TASE",
          "",
          512157603,
          "אופנה והלבשה",
          "שקל חדש",
          2050.0,
          6216.0,
          0.0,
          127.43,
          0.0002,
          0.0015,
          0.0007
        ],
        [
          "פמס",
          315010,
          "TASE",
          "",
          520037284,
          "אופנה והלבשה",
          "שקל חדש",
          816.0,
          11420.0,
          0.0,
          93.19,
          0.0001,
          0.0011,
          0.0005
        ],
        [
          "אינרום",
          1132356,
          "TASE",
          "",
          515001659,
          "מתכת ומוצרי בניה",
          "שקל חדש",
          27597.0,
          1630.0,
          0.0,
          449.83,
          0.0003,
          0.0054,
          0.0023
        ],
        [
          "המלט",
          1080324,
          "TASE",
          "",
          520041575,
          "מתכת ומוצרי בניה",
          "שקל חדש",
          1595.0,
          7323.0,
          0.0,
          116.8,
          0.0001,
          0.0014,
          0.0006
        ],
        [
          "קליל",
          797035,
          "TASE",
          "",
          520032442,
          "מתכת ומוצרי בניה",
          "שקל חדש",
          272.0,
          33640.0,
          0.0,
          91.5,
          0.0001,
          0.0011,
          0.0005
        ],
        [
          "שפיר הנדסה",
          1133875,
          "TASE",
          "",
          514892801,
          "מתכת ומוצרי בניה",
          "שקל חדש",
          31112.0,
          1122.0,
          5.29,
          354.37,
          0.0001,
          0.0042,
          0.0018
        ],
        [
          "ארד",
          1091651,
          "TASE",
          "",
          510007800,
          "אלקטרוניקה ואופטיקה",
          "שקל חדש",
          2195.0,
          3493.0,
          1.72,
          78.39,
          0.0001,
          0.0009,
          0.0004
        ],
        [
          "מיטרוניקס",
          1091065,
          "TASE",
          "",
          511527202,
          "אלקטרוניקה ואופטיקה",
          "שקל חדש",
          12287.0,
          1735.0,
          0.0,
          213.18,
          0.0001,
          0.0025,
          0.0011
        ],
        [
          "פלסאון תעשיות",
          1081603,
          "TASE",
          "",
          520042912,
          "כימיה גומי ופלסטיק",
          "שקל חדש",
          847.0,
          16140.0,
          0.0,
          136.71,
          0.0001,
          0.0016,
          0.0007
        ],
        [
          "אבגול",
          1100957,
          "TASE",
          "",
          510119068,
          "עץ נייר ודפוס",
          "שקל חדש",
          26160.0,
          345.6,
          3.43,
          93.84,
          0.0001,
          0.0011,
          0.0005
        ],
        [
          "נייר חדרה",
          632018,
          "TASE",
          "",
          520018383,
          "עץ נייר ודפוס",
          "שקל חדש",
          729.0,
          24910.0,
          0.0,
          181.59,
          0.0001,
          0.0022,
          0.0009
        ],
        [
          "ספאנטק",
          1090117,
          "TASE",
          "",
          512288713,
          "עץ נייר ודפוס",
          "שקל חדש",
          5881.0,
          933.7,
          0.0,
          54.91,
          0.0001,
          0.0007,
          0.0003
        ],
        [
          "שלאג",
          1090547,
          "TASE",
          "",
          513507574,
          "עץ נייר ודפוס",
          "שקל חדש",
          4194.0,
          1512.0,
          0.0,
          63.41,
          0.0001,
          0.0008,
          0.0003
        ],
        [
          "אייאיאס תעש",
          431015,
          "TASE",
          "",
          520039132,
          "השקעה ואחזקות",
          "שקל חדש",
          590.0,
          17030.0,
          0.71,
          101.19,
          0.0001,
          0.0012,
          0.0005
        ],
        [
          "אלקו החזקות",
          694034,
          "TASE",
          "",
          520025370,
          "השקעה ואחזקות",
          "שקל חדש",
          3152.0,
          7314.0,
          0.0,
          230.54,
          0.0001,
          0.0027,
          0.0012
        ],
        [
          "אלקטרה",
          739037,
          "TASE",
          "",
          520028911,
          "השקעה ואחזקות",
          "שקל חדש",
          549.0,
          88000.0,
          0.0,
          483.12,
          0.0001,
          0.0058,
          0.0025
        ],
        [
          "אקויטל",
          755017,
          "TASE",
          "",
          520030859,
          "השקעה ואחזקות",
          "שקל חדש",
          1038.0,
          9021.0,
          0.0,
          93.64,
          0.0001,
          0.0011,
          0.0005
        ],
        [
          "יואל",
          583013,
          "TASE",
          "",
          520033226,
          "השקעה ואחזקות",
          "שקל חדש",
          2628.0,
          19500.0,
          0.0,
          512.46,
          0.0001,
          0.0061,
          0.0026
        ],
        [
          "מבטח שמיר",
          127019,
          "TASE",
          "",
          520034125,
          "השקעה ואחזקות",
          "שקל חדש",
          1448.0,
          7523.0,
          0.0,
          108.93,
          0.0001,
          0.0013,
          0.0006
        ],
        [
          "צור שמיר",
          730010,
          "TASE",
          "",
          520025586,
          "השקעה ואחזקות",
          "שקל חדש",
          5669.0,
          1545.0,
          0.0,
          87.59,
          0.0001,
          0.001,
          0.0005
        ],
        [
          "קנון",
          1134139,
          "TASE",
          "",
          515163335,
          "השקעה ואחזקות",
          "שקל חדש",
          4776.0,
          5672.0,
          0.0,
          270.89,
          0.0001,
          0.0032,
          0.0014
        ],
        [
          "נפטא",
          643015,
          "TASE",
          "",
          520020942,
          "חיפושי נפט וגז",
          "שקל חדש",
          11189.0,
          2275.0,
          0.0,
          254.55,
          0.0001,
          0.003,
          0.0013
        ],
        [
          "רציו יהש",
          394015,
          "TASE",
          "",
          550012777,
          "חיפושי נפט וגז",
          "שקל חדש",
          211922.0,
          271.1,
          0.0,
          574.52,
          0.0002,
          0.0068,
          0.003
        ],
        [
          "תמר פטרוליום",
          1141357,
          "TASE",
          "",
          550258438,
          "חיפושי נפט וגז",
          "שקל חדש",
          10144.0,
          1735.0,
          12.9,
          188.9,
          0.0001,
          0.0023,
          0.001
        ],
        [
          "דש איפקס",
          1081843,
          "TASE",
          "",
          520043795,
          "שירותים פיננסיים",
          "שקל חדש",
          7771.0,
          1123.0,
          1.55,
          88.82,
          0.0001,
          0.0011,
          0.0005
        ],
        [
          "לידר שוקי הון",
          1096106,
          "TASE",
          "",
          513773564,
          "שירותים פיננסיים",
          "שקל חדש",
          2240.0,
          4081.0,
          0.0,
          91.41,
          0.0002,
          0.0011,
          0.0005
        ],
        [
          "נאוי",
          208017,
          "TASE",
          "",
          520036070,
          "שירותים פיננסיים",
          "שקל חדש",
          6640.0,
          1852.0,
          0.0,
          122.97,
          0.0002,
          0.0015,
          0.0006
        ],
        [
          "בי קומיוניקיישנס",
          1107663,
          "TASE",
          "",
          512832742,
          "תקשורת ומדיה",
          "שקל חדש",
          3411.0,
          4604.0,
          0.0,
          157.04,
          0.0001,
          0.0019,
          0.0008
        ],
        [
          "אופיסי מניה",
          1141571,
          "TASE",
          "",
          514401702,
          "אנרגיה",
          "שקל חדש",
          6689.0,
          1852.0,
          0.0,
          123.88,
          0.0001,
          0.0015,
          0.0006
        ],
        [
          "ארקו החזקות",
          310011,
          "TASE",
          "",
          520037367,
          "אנרגיה",
          "שקל חדש",
          86531.0,
          196.6,
          0.0,
          170.12,
          0.0001,
          0.002,
          0.0009
        ],
        [
          "דור אלון",
          1093202,
          "TASE",
          "",
          520043878,
          "אנרגיה",
          "שקל חדש",
          1409.0,
          4599.0,
          0.0,
          64.8,
          0.0001,
          0.0008,
          0.0003
        ],
        [
          "אפקון",
          578013,
          "TASE",
          "",
          520033473,
          "חשמל",
          "שקל חדש",
          522.0,
          15490.0,
          0.0,
          80.86,
          0.0001,
          0.001,
          0.0004
        ],
        [
          "לייבפרסון",
          1123017,
          "TASE",
          "",
          512796756,
          "תוכנה ואינטרנט",
          "שקל חדש",
          14033.0,
          5559.0,
          0.0,
          780.09,
          0.0002,
          0.0093,
          0.004
        ],
        [
          "מגיק",
          1082312,
          "TASE",
          "",
          520036740,
          "תוכנה ואינטרנט",
          "שקל חדש",
          6765.0,
          2865.0,
          0.0,
          193.82,
          0.0002,
          0.0023,
          0.001
        ],
        [
          "ספיאנס",
          1087659,
          "TASE",
          "",
          53368,
          "תוכנה ואינטרנט",
          "שקל חדש",
          7571.0,
          3085.0,
          0.0,
          233.57,
          0.0001,
          0.0028,
          0.0012
        ],
        [
          "נובה",
          1084557,
          "TASE",
          "",
          511812463,
          "מוליכים למחצה",
          "שקל חדש",
          7075.0,
          9438.0,
          0.0,
          667.74,
          0.0003,
          0.008,
          0.0034
        ],
        [
          "ביוטיים",
          1136365,
          "TASE",
          "",
          1651,
          "ביוטכנולוגיה",
          "שקל חדש",
          22490.0,
          869.4,
          0.0,
          195.53,
          0.0002,
          0.0023,
          0.001
        ],
        [
          "קמהדע",
          1094119,
          "TASE",
          "",
          511524605,
          "ביוטכנולוגיה",
          "שקל חדש",
          8169.0,
          1609.0,
          0.0,
          131.44,
          0.0002,
          0.0016,
          0.0007
        ],
        [
          "וואן תוכנה",
          161018,
          "TASE",
          "",
          520034695,
          "שירותי מידע",
          "שקל חדש",
          775.0,
          13800.0,
          1.5,
          108.45,
          0.0001,
          0.0013,
          0.0006
        ],
        [
          "חילן טק",
          1084698,
          "TASE",
          "",
          520039942,
          "שירותי מידע",
          "שקל חדש",
          4561.0,
          7792.0,
          0.0,
          355.39,
          0.0002,
          0.0042,
          0.0018
        ],
        [
          "מטריקס",
          445015,
          "TASE",
          "",
          520039413,
          "שירותי מידע",
          "שקל חדש",
          9372.0,
          3955.0,
          0.0,
          370.66,
          0.0002,
          0.0044,
          0.0019
        ],
        [
          "פורמולה",
          256016,
          "TASE",
          "",
          520036690,
          "שירותי מידע",
          "שקל חדש",
          2988.0,
          12780.0,
          0.0,
          381.87,
          0.0002,
          0.0046,
          0.002
        ],
        [
          "תים",
          156018,
          "TASE",
          "",
          520034620,
          "שירותי מידע",
          "שקל חדש",
          194.0,
          37760.0,
          0.0,
          73.25,
          0.0001,
          0.0009,
          0.0004
        ],
        [
          "אודיוקודס",
          1082965,
          "TASE",
          "",
          520044132,
          "ציוד תקשורת",
          "שקל חדש",
          5808.0,
          2535.0,
          0.0,
          147.23,
          0.0001,
          0.0018,
          0.0008
        ],
        [
          "גילת",
          1082510,
          "TASE",
          "",
          520038936,
          "ציוד תקשורת",
          "שקל חדש",
          8329.0,
          3000.0,
          0.0,
          249.87,
          0.0002,
          0.003,
          0.0013
        ],
        [
          "אנרגיקס",
          1123355,
          "TASE",
          "",
          513901371,
          "קלינטק",
          "שקל חדש",
          33227.0,
          340.0,
          0.0,
          112.97,
          0.0001,
          0.0013,
          0.0006
        ],
        [
          "סהר אינווסט",
          720011,
          "TASE",
          "",
          520041146,
          "קלינטק",
          "שקל חדש",
          101926.0,
          174.8,
          0.0,
          178.17,
          0.0002,
          0.0021,
          0.0009
        ]
      ]
    },
    "תעודות סל": {
      "columns": [
        "שם נ\"ע",
        "מספר ני\"ע",
        "זירת מסחר",
        "מספר מנפיק",
        "ענף מסחר",
        "סוג מטבע",
        "ערך נקוב",
        "שער",
        "פידיון/ריבית לקבל",
        "שווי שוק",
        "שעור מערך נקוב מונפק",
        "שיעור מנכסי אפיק ההשקעה",
        "שעור מנכסי השקעה"
      ],
      "data": [
        [
          "פסגות סל תא 100 סד2",
          1125327,
          "TASE",
          513665661,
          "מדדי מניות בארץ",
          "שקל חדש",
          642000,
          1299,
          0.0,
          8339.58,
          0.0025,
          0.0937,
          0.043
        ],
        [
          "קסם1.ס33 (*) (*)",
          1117266,
          "TASE",
          513502211,
          "מדדי מניות בארץ",
          "שקל חדש",
          4000,
          13010,
          0.0,
          520.4,
          0.0,
          0.0058,
          0.0027
        ],
        [
          "קסם 600 STOXX EUROPE (*) (*)",
          1130202,
          "TASE",
          513502211,
          "מדדי מניות בחול",
          "שקל חדש",
          88650,
          32470,
          0.0,
          28784.65,
          0.0372,
          0.3234,
          0.1485
        ],
        [
          "קסם MSCI שווקים מתעו (*) (*)",
          1117092,
          "TASE",
          513502211,
          "מדדי מניות בחול",
          "שקל חדש",
          56000,
          3648,
          0.0,
          2042.88,
          0.0016,
          0.023,
          0.0105
        ],
        [
          "קסם שקלי 500TR S&P (*) (*)",
          1117639,
          "TASE",
          513502211,
          "מדדי מניות בחול",
          "שקל חדש",
          84408,
          2856,
          0.0,
          2410.69,
          0.0007,
          0.0271,
          0.0124
        ],
        [
          "קסספ.ס39 (*) (*)",
          1117324,
          "TASE",
          513502211,
          "מדדי מניות בחול",
          "שקל חדש",
          130090,
          9419,
          0.0,
          12253.18,
          0.0027,
          0.1377,
          0.0632
        ],
        [
          "ISHARES EMERGIN",
          "US4642872349",
          "NYSE",
          "",
          "מדדי מניות בחול",
          "דולר אמריקאי",
          55670,
          4828,
          0.0,
          9444.75,
          0.0001,
          0.1061,
          0.0487
        ],
        [
          "NOMURA TOPIX",
          "JP3027630007",
          "TSE",
          "",
          "מדדי מניות בחול",
          "יין יפני",
          128640,
          177000,
          0.0,
          7511.59,
          0.0,
          0.0844,
          0.0387
        ],
        [
          "SPDR S&P 500 ET",
          "US78462F1030",
          "NYSE",
          "",
          "מדדי מניות בחול",
          "דולר אמריקאי",
          19076,
          26315,
          55.14,
          17694.89,
          0.0,
          0.1988,
          0.0913
        ]
      ]
    },
    "חוזים עתידיים": {
      "columns": [
        "שם נ\"ע",
        "מספר ני\"ע",
        "זירת מסחר",
        "ענף מסחר",
        "סוג מטבע",
        "ערך נקוב",
        "שער",
        "שווי שוק",
        "שיעור מנכסי אפיק ההשקעה",
        "שעור מנכסי השקעה"
      ],
      "data": [
        [
          "F6/18 MINI S&P500",
          "ESH7",
          "אחר",
          "ל.ר.",
          "דולר אמריקאי",
          31,
          264300,
          -794.67,
          1,
          -0.0041
        ]
      ]
    },
    "לא סחיר - מניות": {
      "columns": [
        "שם נ\"ע",
        "מספר ני\"ע",
        "ספק מידע",
        "מספר מנפיק",
        "ענף מסחר",
        "סוג מטבע",
        "ערך נקוב",
        "שער",
        "שווי הוגן",
        "שעור מערך נקוב מונפק",
        "שיעור מנכסי אפיק ההשקעה",
        "שעור מנכסי השקעה"
      ],
      "data": [
        [
          "אייס אוטו דיפו מניה",
          1107523,
          "",
          511739294,
          "השקעה ואחזקות",
          "שקל חדש",
          1221.0,
          0.0,
          0.0,
          0.0001,
          0,
          0.0
        ],
        [
          "מגנ\"א בי.אס.פי מניה ל\"ס",
          222100513,
          "",
          "",
          "ביטחוניות",
          "שקל חדש",
          51.5,
          784836.18,
          404.19,
          "",
          1,
          0.0021
        ]
      ]
    },
    "לא סחיר - כתבי אופציה": {
      "columns": [
        "שם נ\"ע",
        "מספר ני\"ע",
        "ענף מסחר",
        "סוג מטבע",
        "תאריך רכישה",
        "ערך נקוב",
        "שער",
        "שווי הוגן",
        "שעור מערך נקוב מונפק",
        "שיעור מנכסי אפיק ההשקעה",
        "שעור מנכסי השקעה"
      ],
      "data": [
        [
          "מגנ\"א אופ.ל.ס.",
          888223393,
          "אחר",
          "שקל חדש",
          "",
          77.25,
          609052.03,
          470.49,
          "",
          1,
          0.0024
        ]
      ]
    },
    "לא סחיר - חוזים עתידיים": {
      "columns": [
        "שם נ\"ע",
        "מספר ני\"ע",
        "ענף מסחר",
        "תאריך רכישה",
        "סוג מטבע",
        "ערך נקוב",
        "שער",
        "שווי הוגן",
        "שיעור מנכסי אפיק ההשקעה",
        "שעור מנכסי השקעה"
      ],
      "data": [
        [
          "FW USD/ILS12/04/18 3.4696 לאומי",
          777103714,
          "ל.ר.",
          "",
          "שקל חדש",
          -45000,
          4.15,
          -1.87,
          0.0076,
          0.0
        ],
        [
          "FW USD/JPY12/04/18 105.92 לאומי",
          777103730,
          "ל.ר.",
          "",
          "יין יפני",
          1300,
          50.32,
          0.02,
          -0.0001,
          0.0
        ],
        [
          "FW040418 EUR/NIS4.30",
          428382634,
          "ל.ר.",
          "29/03/2018",
          "שקל חדש",
          -5530000,
          2.46,
          -135.85,
          0.554,
          -0.0007
        ],
        [
          "FW040418 JPY/NIS3.29",
          428382535,
          "ל.ר.",
          "29/03/2018",
          "שקל חדש",
          -160000000,
          0.01,
          -22.45,
          0.0916,
          -0.0001
        ],
        [
          "FW240418 GBP/NIS4.92",
          428387989,
          "ל.ר.",
          "29/03/2018",
          "שקל חדש",
          600000,
          2.19,
          13.13,
          -0.0536,
          0.0001
        ],
        [
          "FW240418 USD/NIS3.50",
          428383277,
          "ל.ר.",
          "29/03/2018",
          "שקל חדש",
          -7800000,
          1.25,
          -97.84,
          0.399,
          -0.0005
        ],
        [
          "FW300318 JPY/NIS3.29",
          428356059,
          "ל.ר.",
          "28/03/2018",
          "שקל חדש",
          -7000000,
          0.01,
          -0.42,
          0.0017,
          0.0
        ],
        [
          "FW EUR/USD 26/07/18 1.2497 לאומי",
          777103623,
          "ל.ר.",
          "",
          "דולר אמריקאי",
          -2900,
          -0.67,
          0.07,
          -0.0003,
          0.0
        ]
      ]
    },
    "הלוואות": {
      "columns": [
        "שם נ\"ע",
        "קונסורציום כן/לא",
        "מספר ני\"ע",
        "מספר מנפיק",
        "דירוג",
        "תאריך רכישה",
        "שם מדרג",
        "מח\"מ",
        "סוג מטבע",
        "שיעור ריבית",
        "תשואה לפידיון",
        "ערך נקוב",
        "שער",
        "שווי הוגן",
        "שיעור מנכסי אפיק ההשקעה",
        "שעור מנכסי השקעה"
      ],
      "data": [
        [
          "הלוואות עמיתים שקלי",
          "לא",
          300737087,
          "",
          "AA+ IL",
          "",
          "S&P מעלות",
          2.63,
          "שקל חדש",
          "",
          0.011,
          1103949.7,
          100.3,
          1107.21,
          1,
          0.0057
        ]
      ]
    },
    "השקעות אחרות": {
      "columns": [
        "שם נ\"ע",
        "מספר ני\"ע",
        "דירוג",
        "שם מדרג",
        "סוג מטבע",
        "שיעור ריבית",
        "תשואה לפידיון",
        "שווי הוגן",
        "שיעור מנכסי אפיק ה השקעה",
        "שעור מנכסי השקעה"
      ],
      "data": [
        [
          "מעבר מיזוגים",
          419250600,
          "NR IL",
          "",
          "שקל חדש",
          "",
          "",
          5.0,
          1.0016,
          0
        ],
        [
          "בנק מעבר נכסים-JPY",
          419259197,
          "NR",
          "",
          "יין יפני",
          "",
          "",
          -0.01,
          -0.0016,
          0
        ]
      ]
    }
  }
}